UART/regmap.vh
/*
References:
https://media.digikey.com/pdf/Data%20Sheets/Texas%20Instruments%20PDFs/PC16550D.pdf
https://www.ti.com/lit/ds/symlink/tl16c550c.pdf
*/
`include "consts.vh"


`define UART_DIV_WIDTH 16    // Divider range bits: 1 to 2**16
`define UART_TICKS_NUM 16
`define UART_FIFO_ADDR_W 4   // 16 byte FIFO

// Choose 8 or 32 bus width:
`define DATA_BUS_WIDTH_8 
`ifdef DATA_BUS_WIDTH_8
    `define UART_ADDR_WIDTH 3
    `define UART_DATA_WIDTH 8
`else
    `define UART_ADDR_WIDTH 5
    `define UART_DATA_WIDTH 32
`endif

// Register map
`define UART_REG_RBR `UART_ADDR_WIDTH'h0 // Receiver Buffer reg     (R only)
`define UART_REG_THR `UART_ADDR_WIDTH'h0 // Transmitter Holding reg (W only)
`define UART_REG_IER `UART_ADDR_WIDTH'h1 // Interrupt enable reg
`define UART_REG_IIR `UART_ADDR_WIDTH'h2 // Interrupt status reg    (R only)
`define UART_REG_FCR `UART_ADDR_WIDTH'h2 // Fifo control reg        (W only)
`define UART_REG_LCR `UART_ADDR_WIDTH'h3 // Line control reg
`define UART_REG_LSR `UART_ADDR_WIDTH'h5 // Line status reg
`define UART_REG_MCR `UART_ADDR_WIDTH'h4 // Modem control reg           /* Unimplemented */
`define UART_REG_MSR `UART_ADDR_WIDTH'h6 // Modem status reg            /* Unimplemented */
`define UART_REG_SPR `UART_ADDR_WIDTH'h7 // Scratch Pad                 /* Unimplemented */
`define UART_REG_DLL `UART_ADDR_WIDTH'h0 // Divisor latch LSB
`define UART_REG_DLM `UART_ADDR_WIDTH'h1 // Divisor latch MSB

// Interrupt Enable register bits (IER)
`define UART_IER_ERBFI  0   // Enable Received Data Available Interrupt (ERBI)
`define UART_IER_ETBEI  1   // Enable Transmitter Holding Register Empty Interrupt (ETBEI)
`define UART_IER_ELSI   2   // Enable Receiver Line Status Interrupt
`define UART_IER_EDSSI  3   // Enable Modem Status Interrupt (EDSSI)    /* Unimplemented */
`define UART_IER_UNUSED 4   // 4 bits

// Interrupt Identification (status) Register bits (IIR, ISR): R only
`define UART_IIR_IPEND  0	    // Interrupt pending when 0
`define UART_IIR_INTID  1	    // Interrupt identification
`define UART_IIR_UNUSED 4
`define UART_IIR_FIFOEN 6	    // FIFO enable. 0 disable, 3 enable

// Interrupt identification values for bits 3:1
`define UART_IIR_RLS	3'b011	// Receiver Line Status
`define UART_IIR_RDA	3'b010	// Receiver Data available
`define UART_IIR_TI	    3'b110	// Char Timeout Indication
`define UART_IIR_THRE	3'b001	// Transmitter Holding Register empty
`define UART_IIR_MS	    3'b000	// Modem Status                         /* Unimplemented */

// Line Status Register bits
`define UART_LSR_DR	    0	    // Data ready
`define UART_LSR_OE	    1	    // Overrun Error
`define UART_LSR_PE	    2	    // Parity Error
`define UART_LSR_FE	    3	    // Framing Error
`define UART_LSR_BI	    4	    // Break interrupt                      /* Unimplemented */
`define UART_LSR_TF     5	    // Transmit FIFO is empty THRE
`define UART_LSR_TE	    6	    // Transmitter Empty indicator TEMT
`define UART_LSR_EI	    7	    // Error in Rx Fifo RXFIFOE

// Line Control register bits
`define UART_LCR_WLS    0       // Word length select bit 0 (WLS1:WLS0)
`define UART_LCR_STB    2	    // stop bits
`define UART_LCR_PEN    3	    // parity enable
`define UART_LCR_EPS    4	    // even parity select
`define UART_LCR_SP     5	    // stick parity
`define UART_LCR_BC     6	    // Break control                        /* Unimplemented */
`define UART_LCR_DL     7	    // Divisor Latch access bit (DLAB)

// Fifo Control register bits (FCR): W only
`define UART_FCR_FIFOEN     0   // FIFO Enable
`define UART_FCR_RXCLR      1   // Receiver FIFO Reset
`define UART_FCR_TXCLR      2   // Transmitter FIFO Reset
`define UART_FCR_DMAMODE    3   // DMA Mode select                      /* Unimplemented */
`define UART_FCR_RXFIFTL    6   // Receiver fifo threshold levels       /* Unimplemented */ always 01

// FIFO threshold trigger level RXFIFTL (RXFIFTM:RXFIFTL) values
`define UART_FCR_TL_1	2'b00
`define UART_FCR_TL_4	2'b01
`define UART_FCR_TL_8	2'b10
`define UART_FCR_TL_14	2'b11

// Modem Control register bits
`define UART_MCR_DTR	0   // Data terminal ready
`define UART_MCR_RTS	1   // Request to send
`define UART_MCR_OUT1	2
`define UART_MCR_OUT2	3
`define UART_MCR_LOOP   4	// Loopback mode enable
`define UART_MCR_AFE    5	// Autoflow control mode enable

// Modem Status Register bits
`define UART_MSR_DCTS	0	// Delta Clear to Send
`define UART_MSR_DDSR	1   // Delta Data Set Ready
`define UART_MSR_TERI	2   // Trailing Edge Ring Indicator
`define UART_MSR_DDCD	3   // Delta Data Carrier Detect
`define UART_MSR_CCTS	4	// Complement Clear to Send
`define UART_MSR_CDSR	5   // Complement Data Set Ready
`define UART_MSR_CRI	6   // Complement Ring indicator
`define UART_MSR_CDCD	7   // Complement Data Carrier Detect

UART/clock_divider.sv
/*
    Clock divider (Baud Rate Generation)

If divider value is unknown then clk out is a constant 1

f="clock_divider.sv"; m="clock_divider";
yosys -p "read_verilog -sv ${f}; hierarchy -check -top $m; proc; opt; clean; show -format svg -prefix ${m} ${m}; show ${m}"
*/
module clock_divider #(parameter DIV_WIDTH = 16) (
    input res_n,
    input clk_in,
    input [DIV_WIDTH-1:0] div,
    output logic clk_out
);
    logic [DIV_WIDTH-1:0] counter, next_count;
    logic cycle_init, cycle_full, switch_clk, half_cycle;

    assign cycle_init   = counter == 1;
    assign cycle_full   = counter == div;
    assign half_cycle   = counter == {1'b0, div[DIV_WIDTH-1:1]};// counter == div >> 1
    assign switch_clk   = cycle_full | half_cycle;              // odd dividers will not get exact 50% phase
    assign next_count   = counter + 1;

    always_ff @(posedge clk_in or negedge res_n) begin
        if (~res_n)
            counter <= 1;
        else if (cycle_full)
            counter <= 1;
        else
            counter <= next_count;
    end
    always_ff @(posedge clk_in or negedge res_n) begin
        if (~res_n)
            clk_out <= 1'b1;
        else if (switch_clk)
            clk_out <= ~clk_out;
        else if ($isunknown(switch_clk))
            clk_out <= 1'b1;
    end
endmodule

UART/testbench/testbench.sv
`include "regmap.vh"
`timescale 1ns / 1ns
`define TCLK 5  // 100Mhz


/*
src="testbench/testbench.sv clock_divider.sv"
iverilog -Wall -g2012 -o vcd/baud_tb.vvp -s baud_tb ${src};
vvp vcd/baud_tb.vvp
*/
module baud_tb;
    logic clk;
    logic res_n;
    logic clk_out2, clk_out3, clk_out4, clk_out5, clk_out6, clk_out7, clk_out8, clk_out9, clk_out10;
    integer cnt2 = 0, cnt3 = 0, cnt4 = 0, cnt5 = 0, cnt6 = 0, cnt7 = 0, cnt8 = 0, cnt9 = 0, cnt10 = 0;

    clock_divider uut2 (.clk_in(clk), .res_n(res_n), .div(16'd2), .clk_out(clk_out2));
    clock_divider uut3 (.clk_in(clk), .res_n(res_n), .div(16'd3), .clk_out(clk_out3));
    clock_divider uut4 (.clk_in(clk), .res_n(res_n), .div(16'd4), .clk_out(clk_out4));
    clock_divider uut5 (.clk_in(clk), .res_n(res_n), .div(16'd5), .clk_out(clk_out5));
    clock_divider uut6 (.clk_in(clk), .res_n(res_n), .div(16'd6), .clk_out(clk_out6));
    clock_divider uut7 (.clk_in(clk), .res_n(res_n), .div(16'd7), .clk_out(clk_out7));
    clock_divider uut8 (.clk_in(clk), .res_n(res_n), .div(16'd8), .clk_out(clk_out8));
    clock_divider uut9 (.clk_in(clk), .res_n(res_n), .div(16'd9), .clk_out(clk_out9));
    clock_divider uut10 (.clk_in(clk), .res_n(res_n), .div(16'd10), .clk_out(clk_out10));

    always #`TCLK clk = ~clk;
    always @(posedge clk_out2) cnt2 = cnt2 + 1;
    always @(posedge clk_out3) cnt3 = cnt3 + 1;
    always @(posedge clk_out4) cnt4 = cnt4 + 1;
    always @(posedge clk_out5) cnt5 = cnt5 + 1;
    always @(posedge clk_out6) cnt6 = cnt6 + 1;
    always @(posedge clk_out7) cnt7 = cnt7 + 1;
    always @(posedge clk_out8) cnt8 = cnt8 + 1;
    always @(posedge clk_out9) cnt9 = cnt9 + 1;
    always @(posedge clk_out10) cnt10 = cnt10 + 1;

    initial begin
        $dumpfile("vcd/baud_tb.vcd");
        $dumpvars(0);
        clk = 1'b1;
        res_n = 1'b1;
        @(posedge clk) res_n = 1'b0;
        @(posedge clk);
        @(posedge clk) res_n = 1'b1;
        repeat(24) @(posedge clk);
        // each clock initial state is 1, so adding 1 to counters
        if (cnt2 != 13) $display("*** [baud_tb] ERROR: cnt2 %0d is not 13", cnt2);
        if (cnt3 != 9) $display("*** [baud_tb] ERROR: cnt3 %0d is not 9", cnt3);
        if (cnt4 != 7) $display("*** [baud_tb] ERROR: cnt4 %0d is not 7", cnt4);
        if (cnt5 != 5) $display("*** [baud_tb] ERROR: cnt5 %0d is not 5", cnt5);
        if (cnt6 != 5) $display("*** [baud_tb] ERROR: cnt6 %0d is not 5", cnt6);
        if (cnt7 != 4) $display("*** [baud_tb] ERROR: cnt7 %0d is not 4", cnt7);
        if (cnt8 != 4) $display("*** [baud_tb] ERROR: cnt8 %0d is not 4", cnt8);
        if (cnt9 != 3) $display("*** [baud_tb] ERROR: cnt9 %0d is not 3", cnt9);
        if (cnt10 != 3) $display("*** [baud_tb] ERROR: cnt10 %0d is not 3", cnt10);
        $display("End of testbench: baud_tb.vcd");
        $finish;
    end
endmodule


/*
src="testbench/testbench.sv uart_rx.sv clock_divider.sv ../modules/shift_reg.v"
iverilog -Wall -g2012 -I ../modules/ -o vcd/uart_rx_tb.vvp -s uart_rx_tb ${src};
vvp vcd/uart_rx_tb.vvp
*/
module uart_rx_tb;
    localparam DATA_WIDTH = 8;
    logic clk;
    logic res_n;
    logic valid;
    logic din;
    logic b_tick;
    logic err_par;
    logic err_fr;
    logic [DATA_WIDTH+1:0] uart_rx_out;
    localparam DIV = 16'h4;
    localparam baud_wait = `TCLK*2*16*DIV;

    clock_divider rx_baud (.clk_in(clk), .res_n(res_n), .div(DIV), .clk_out(b_tick));

    uart_rx dut (
        .clk(clk),
        .res_n(res_n),
        .rx_baud(b_tick),
        .rx_din(din),
        .lcreg(8'b00001111),
        .rx_out(uart_rx_out),
        .rx_ready(valid)
    );

    always #`TCLK clk  = ~clk;
    assign err_par = uart_rx_out[8];
    assign err_fr = uart_rx_out[9];

    task driver(input logic [DATA_WIDTH-1:0] tx_data);
        int i;
        begin
            // start bit
            #baud_wait din = 1'b0;
            // data bits
            for (i = 0; i < DATA_WIDTH; i = i + 1)    
                #baud_wait din = tx_data[i];
            // parity
            #baud_wait din = ^tx_data;
            // stop bits
            #baud_wait din = 1'b1;
            #baud_wait din = 1'b1;
            if (uart_rx_out != {err_fr, err_par, tx_data})
                $display("*** [uart_rx_tb] ERROR: uart_rx_out %0h is not as expected %0h", uart_rx_out, {err_fr, err_par, tx_data});
            if (^uart_rx_out[8:0])
                $display("*** [uart_rx_tb] ERROR: parity bit %0b is not correct", err_par);
            // some wait
            #baud_wait;
            #baud_wait;
        end
    endtask

    initial begin
        $dumpfile("vcd/uart_rx_tb.vcd");
        $dumpvars(0);
        $monitor("%t RX: din=%0b dout=%10b, rx_ready=%0b, err_par=%0b, err_fr=%0b", $time, din, uart_rx_out, valid, err_par, err_fr);
        clk = 1'b1;
        res_n = 1'b1;
        @(posedge clk) res_n = 1'b0;
        repeat(2) @(posedge clk);
        res_n = 1'b1;
        din = 1'b1;
        driver(8'hB2);
        driver(8'hAA);
        driver(8'h95);
        $display("End of testbench: uart_rx_tb.vcd");
        $finish;
    end
endmodule


/*
src="testbench/testbench.sv uart_tx.sv clock_divider.sv ../modules/shift_reg.v"
iverilog -Wall -g2012 -I ../modules/ -o vcd/uart_tx_tb.vvp -s uart_tx_tb ${src};
vvp vcd/uart_tx_tb.vvp
*/
module uart_tx_tb;
    logic clk;
    logic res_n;
    logic en;
    logic uart_tx_out;
    logic valid;
    logic b_tick;
    logic [7:0] din;
    localparam DIV = 16'd4;
    logic [11:0] tsr_data;
    logic sreg_clk;
    logic [3:0] cnt;

    clock_divider tx_baud (.clk_in(clk), .res_n(res_n), .div(DIV), .clk_out(b_tick));

    shift_reg #(.N(12)) tb_thr (
        .clk(sreg_clk),
        .res_n(res_n),
        .en(en),
        .din(uart_tx_out),
        .dout(tsr_data)
    );

    uart_tx dut (
        .clk(clk),
        .res_n(res_n),
        .tx_baud(b_tick),
        .tx_start(en),
        .tx_din(din),
        .lcreg(8'b0001_1111),
        .tx_dout(uart_tx_out),
        .tx_ready(valid),
        .tsr_data()
    );

    always #`TCLK clk  = ~clk;

    assign sreg_clk = cnt == 7;

    always_ff @(posedge b_tick or negedge res_n) begin
        if (~res_n | cnt == 15)
            cnt <= 0;
        else
            cnt <= cnt + 1;
    end

    initial begin
        $dumpfile("vcd/uart_tx_tb.vcd");
        $dumpvars(0);
        $monitor("%t TX: din=%0b dout=%0b", $time, din, uart_tx_out);
        clk = 1'b1;
        res_n = 1'b1;
        @(posedge clk) res_n = 1'b0;
        repeat(2) @(posedge clk);
        res_n = 1'b1;
        //@(posedge clk) res_n = 1'b0;
        repeat(16*DIV) @(posedge clk);
        din = 8'hC2;
        en = 1'b1;
        @(posedge valid);
        @(posedge valid);
        if (tsr_data !== 'b110110000100)
            $display("*** [uart_tx_tb] ERROR: tx dout %0b is not as expected", tsr_data);
        else
            $display("PASSED: tx dout %0h is correct!", tsr_data);
        din = 8'hA9;
        @(posedge valid);
        if (tsr_data !== 'b111101010010)
            $display("*** [uart_tx_tb] ERROR: tx dout %0b is not as expected", tsr_data);
        else 
            $display("PASSED: tx dout %0h is correct!", tsr_data);
        repeat(48*DIV) @(posedge clk);
        $display("End of testbench: uart_tx_tb.vcd");
        $finish;
    end
endmodule


/*
src="testbench/testbench.sv uart.sv clock_divider.sv uart_tx.sv uart_rx.sv ../modules/fifo.v ../modules/shift_reg.v"
iverilog -Wall -g2012 -I ../modules/ -o vcd/uart_tb.vvp -s uart_tb ${src};
vvp vcd/uart_tb.vvp
*/
module uart_tb;
    localparam DWIDTH = 8;
    int byte_wait;
    logic clk;
    logic res_n;
    logic [15:0] divisor;
    logic rd_uart;
    logic wr_uart;
    logic tx_ext;
    logic rx_empty;
    logic tx_full;
    logic [DWIDTH-1:0] wr_data;
    logic [DWIDTH-1:0] tsr_data;
    logic [DWIDTH-1:0] lcreg;
    logic [DWIDTH+1:0] rd_data;
    logic rx_ready;
    logic rx_full;
    logic tx_empty;
    logic tx_ready;

    uart uut (
        .clk(clk),
        .res_n(res_n),
        .divisor(divisor),
        .wr_data(wr_data),
        .rd_uart(rd_uart),
        .wr_uart(wr_uart),
        .rx_ext(tx_ext),
        .tx_ext(tx_ext),
        .rx_empty(rx_empty),
        .tx_full(tx_full),
        .rd_data(rd_data),
        .tsr_data(tsr_data),
        .rx_ready(rx_ready),
        .rx_full(rx_full),
        .tx_empty(tx_empty),
        .tx_ready(tx_ready),
        .lcreg(lcreg),
        .fcreg(8'b0000_0001)
    );

    task expect_result;
        input integer exp_val;
        begin
            wait(rx_empty == 1'b0);
            wait(rx_empty == 1'b1);
            if (rd_data !== exp_val) $display("*** [uart_tb] ERROR: rd_data %0h is not %0h", rd_data, exp_val);
            else $display("PASSED: rd_data 0x%0h is correct!", rd_data);
        end
    endtask
    
    always #`TCLK clk = ~clk;
    assign rd_uart = ~rx_empty;

    initial begin
        $dumpfile("vcd/UART_VTB.vcd");
        $dumpvars();
        $monitor("%t [uart_tb] INFO: wr_data=%0h  rd_data=%0h  rx_ready=%0b", $time, wr_data, rd_data, rx_ready);
        clk = 0;
        res_n = 1;
        divisor = 430; // 100mhz / 16*(9600*12/8)
        byte_wait = divisor * 16 * 10;
        @(posedge clk) res_n = 0;
        @(posedge clk) res_n = 1;
        lcreg = 8'b0001_1111;  // even parity
        @(negedge clk) wr_uart = 1;
        wr_data = 'hAB;
        @(negedge clk) wr_uart = 0;
        expect_result(wr_data);
        
        $display("Pausing before next tx");
        repeat(byte_wait) @(negedge clk);
        $display("Proceeding");
        lcreg = 8'b0000_1111; // odd parity

        @(negedge clk) wr_uart = 1;
        wr_data = 'hDA;
        @(negedge clk) wr_data = 'hC2;
        @(negedge clk) wr_data = 'hB9;
        @(negedge clk) wr_data = 'hB2;
        @(negedge clk) wr_uart = 0;

        //repeat(byte_wait * 5) @(posedge clk);
        expect_result('hDA);
        expect_result('hC2);
        expect_result('hB9);
        expect_result('hB2);

        repeat(byte_wait) @(posedge clk);
        $display("End of testbench: UART_VTB.vcd");
        $finish;
    end
endmodule


/*
src="testbench/testbench.sv uart_top.sv uart.sv clock_divider.sv uart_tx.sv uart_rx.sv ../modules/fifo.v ../modules/shift_reg.v"
iverilog -Wall -g2012 -I ../modules/ -o vcd/uart_top_tb.vvp -s uart_top_tb ${src};
vvp vcd/uart_top_tb.vvp
*/
module uart_top_tb;
    logic clk = 1'b1;
    logic res = 1'b1;
    logic wr, rd, ddis;
    logic [`UART_ADDR_WIDTH-1:0] addr;
    wire [`UART_DATA_WIDTH-1:0] data_bus;
    logic [`UART_DATA_WIDTH-1:0] dutin, dutout;

    uart_top dut (
        .clk(clk),              // system clock pin
        .cs(1'b1),             // rx baud pin
        .res(res),              // master reset pin
        .wr(wr),               // write enable pin
        .rd(rd),               // read enable pin
        .ddis(ddis),             // Driver disable high when cpu is writing
        .addr(addr),
        .data_bus(data_bus)
    );
    assign data_bus = ddis ? dutin : {`UART_DATA_WIDTH{1'bZ}};
    assign dutout = data_bus;

    always #`TCLK clk = ~clk;
    initial begin
        $dumpfile("vcd/uart_top_tb.vcd");
        $dumpvars();
        $monitor("%t: addr=%0h  BUS=0x%0h", $time, addr, dutout);
        @(posedge clk) res = 0;
        @(negedge clk);

        // input to LCR:
        ddis = 1;
        wr = 1;
        addr = 3;   // lcr
        dutin = 'h80;
        @(negedge clk) if (dutout != 'h80)
            $display("*** [uart_top_tb] ERROR: uart_top data_bus is not 0x80");
        
        // input to DLL:
        addr = 0; dutin = 'h40;
        @(negedge clk) if (dutout != 'h40)
            $display("*** [uart_top_tb] ERROR: uart_top data_bus is not 0x80");
    
        // output LCR:
        ddis = 0;
        wr = 0;
        rd = 1;
        addr = 3;
        @(negedge clk) if (dutout != 'h80)
            $display("*** [uart_top_tb] ERROR: uart data_bus is not 0x80");
        $display("End of testbench: uart_top_tb.vcd");
        $finish;
    end
endmodule

UART/vcd/baud_tb.vcd
$version Generated by VerilatedVcd $end
$timescale 1ns $end
 $scope module baud_tb $end
  $var wire 1 " clk $end
  $var wire 1 # res_n $end
  $var wire 1 $ clk_out2 $end
  $var wire 1 % clk_out3 $end
  $var wire 1 & clk_out4 $end
  $var wire 1 ' clk_out5 $end
  $var wire 1 ( clk_out6 $end
  $var wire 1 ) clk_out7 $end
  $var wire 1 * clk_out8 $end
  $var wire 1 + clk_out9 $end
  $var wire 1 , clk_out10 $end
  $var wire 32 - cnt2 [31:0] $end
  $var wire 32 . cnt3 [31:0] $end
  $var wire 32 / cnt4 [31:0] $end
  $var wire 32 0 cnt5 [31:0] $end
  $var wire 32 1 cnt6 [31:0] $end
  $var wire 32 2 cnt7 [31:0] $end
  $var wire 32 3 cnt8 [31:0] $end
  $var wire 32 4 cnt9 [31:0] $end
  $var wire 32 5 cnt10 [31:0] $end
  $scope module uut10 $end
   $var wire 32 )! DIV_WIDTH [31:0] $end
   $var wire 1 6 res_n $end
   $var wire 1 7 clk_in $end
   $var wire 16 *! div [15:0] $end
   $var wire 1 8 clk_out $end
   $var wire 16 9 counter [15:0] $end
   $var wire 16 : next_count [15:0] $end
   $var wire 1 ; cycle_init $end
   $var wire 1 < cycle_full $end
   $var wire 1 = switch_clk $end
   $var wire 1 > half_cycle $end
  $upscope $end
  $scope module uut2 $end
   $var wire 32 )! DIV_WIDTH [31:0] $end
   $var wire 1 ? res_n $end
   $var wire 1 @ clk_in $end
   $var wire 16 +! div [15:0] $end
   $var wire 1 A clk_out $end
   $var wire 16 B counter [15:0] $end
   $var wire 16 C next_count [15:0] $end
   $var wire 1 D cycle_init $end
   $var wire 1 E cycle_full $end
   $var wire 1 F switch_clk $end
   $var wire 1 G half_cycle $end
  $upscope $end
  $scope module uut3 $end
   $var wire 32 )! DIV_WIDTH [31:0] $end
   $var wire 1 H res_n $end
   $var wire 1 I clk_in $end
   $var wire 16 ,! div [15:0] $end
   $var wire 1 J clk_out $end
   $var wire 16 K counter [15:0] $end
   $var wire 16 L next_count [15:0] $end
   $var wire 1 M cycle_init $end
   $var wire 1 N cycle_full $end
   $var wire 1 O switch_clk $end
   $var wire 1 P half_cycle $end
  $upscope $end
  $scope module uut4 $end
   $var wire 32 )! DIV_WIDTH [31:0] $end
   $var wire 1 Q res_n $end
   $var wire 1 R clk_in $end
   $var wire 16 -! div [15:0] $end
   $var wire 1 S clk_out $end
   $var wire 16 T counter [15:0] $end
   $var wire 16 U next_count [15:0] $end
   $var wire 1 V cycle_init $end
   $var wire 1 W cycle_full $end
   $var wire 1 X switch_clk $end
   $var wire 1 Y half_cycle $end
  $upscope $end
  $scope module uut5 $end
   $var wire 32 )! DIV_WIDTH [31:0] $end
   $var wire 1 Z res_n $end
   $var wire 1 [ clk_in $end
   $var wire 16 .! div [15:0] $end
   $var wire 1 \ clk_out $end
   $var wire 16 ] counter [15:0] $end
   $var wire 16 ^ next_count [15:0] $end
   $var wire 1 _ cycle_init $end
   $var wire 1 ` cycle_full $end
   $var wire 1 a switch_clk $end
   $var wire 1 b half_cycle $end
  $upscope $end
  $scope module uut6 $end
   $var wire 32 )! DIV_WIDTH [31:0] $end
   $var wire 1 c res_n $end
   $var wire 1 d clk_in $end
   $var wire 16 /! div [15:0] $end
   $var wire 1 e clk_out $end
   $var wire 16 f counter [15:0] $end
   $var wire 16 g next_count [15:0] $end
   $var wire 1 h cycle_init $end
   $var wire 1 i cycle_full $end
   $var wire 1 j switch_clk $end
   $var wire 1 k half_cycle $end
  $upscope $end
  $scope module uut7 $end
   $var wire 32 )! DIV_WIDTH [31:0] $end
   $var wire 1 l res_n $end
   $var wire 1 m clk_in $end
   $var wire 16 0! div [15:0] $end
   $var wire 1 n clk_out $end
   $var wire 16 o counter [15:0] $end
   $var wire 16 p next_count [15:0] $end
   $var wire 1 q cycle_init $end
   $var wire 1 r cycle_full $end
   $var wire 1 s switch_clk $end
   $var wire 1 t half_cycle $end
  $upscope $end
  $scope module uut8 $end
   $var wire 32 )! DIV_WIDTH [31:0] $end
   $var wire 1 u res_n $end
   $var wire 1 v clk_in $end
   $var wire 16 1! div [15:0] $end
   $var wire 1 w clk_out $end
   $var wire 16 x counter [15:0] $end
   $var wire 16 y next_count [15:0] $end
   $var wire 1 z cycle_init $end
   $var wire 1 { cycle_full $end
   $var wire 1 | switch_clk $end
   $var wire 1 } half_cycle $end
  $upscope $end
  $scope module uut9 $end
   $var wire 32 )! DIV_WIDTH [31:0] $end
   $var wire 1 ~ res_n $end
   $var wire 1 !! clk_in $end
   $var wire 16 2! div [15:0] $end
   $var wire 1 "! clk_out $end
   $var wire 16 #! counter [15:0] $end
   $var wire 16 $! next_count [15:0] $end
   $var wire 1 %! cycle_init $end
   $var wire 1 &! cycle_full $end
   $var wire 1 '! switch_clk $end
   $var wire 1 (! half_cycle $end
  $upscope $end
 $upscope $end
$enddefinitions $end


#0
1"
1#
0$
0%
0&
0'
0(
0)
0*
0+
0,
b00000000000000000000000000000000 -
b00000000000000000000000000000000 .
b00000000000000000000000000000000 /
b00000000000000000000000000000000 0
b00000000000000000000000000000000 1
b00000000000000000000000000000000 2
b00000000000000000000000000000000 3
b00000000000000000000000000000000 4
b00000000000000000000000000000000 5
16
17
08
b0000000000000001 9
b0000000000000010 :
1;
0<
0=
0>
1?
1@
0A
b0000000000000001 B
b0000000000000010 C
1D
0E
1F
1G
1H
1I
0J
b0000000000000001 K
b0000000000000010 L
1M
0N
1O
1P
1Q
1R
0S
b0000000000000001 T
b0000000000000010 U
1V
0W
0X
0Y
1Z
1[
0\
b0000000000000001 ]
b0000000000000010 ^
1_
0`
0a
0b
1c
1d
0e
b0000000000000001 f
b0000000000000010 g
1h
0i
0j
0k
1l
1m
0n
b0000000000000001 o
b0000000000000010 p
1q
0r
0s
0t
1u
1v
0w
b0000000000000001 x
b0000000000000010 y
1z
0{
0|
0}
1~
1!!
0"!
b0000000000000001 #!
b0000000000000010 $!
1%!
0&!
0'!
0(!
b00000000000000000000000000010000 )!
b0000000000001010 *!
b0000000000000010 +!
b0000000000000011 ,!
b0000000000000100 -!
b0000000000000101 .!
b0000000000000110 /!
b0000000000000111 0!
b0000000000001000 1!
b0000000000001001 2!
#5
0"
07
0@
0I
0R
0[
0d
0m
0v
0!!
#10
1"
0#
1$
1%
1&
1'
1(
1)
1*
1+
1,
b00000000000000000000000000000001 -
b00000000000000000000000000000001 .
b00000000000000000000000000000001 /
b00000000000000000000000000000001 0
b00000000000000000000000000000001 1
b00000000000000000000000000000001 2
b00000000000000000000000000000001 3
b00000000000000000000000000000001 4
b00000000000000000000000000000001 5
06
17
18
0?
1@
1A
0H
1I
1J
0Q
1R
1S
0Z
1[
1\
0c
1d
1e
0l
1m
1n
0u
1v
1w
0~
1!!
1"!
#15
0"
07
0@
0I
0R
0[
0d
0m
0v
0!!
#20
1"
17
1@
1I
1R
1[
1d
1m
1v
1!!
#25
0"
07
0@
0I
0R
0[
0d
0m
0v
0!!
#30
1"
1#
0$
0%
16
17
b0000000000000010 9
b0000000000000011 :
0;
1?
1@
0A
b0000000000000010 B
b0000000000000011 C
0D
1E
0G
1H
1I
0J
b0000000000000010 K
b0000000000000011 L
0M
0O
0P
1Q
1R
b0000000000000010 T
b0000000000000011 U
0V
1X
1Y
1Z
1[
b0000000000000010 ]
b0000000000000011 ^
0_
1a
1b
1c
1d
b0000000000000010 f
b0000000000000011 g
0h
1l
1m
b0000000000000010 o
b0000000000000011 p
0q
1u
1v
b0000000000000010 x
b0000000000000011 y
0z
1~
1!!
b0000000000000010 #!
b0000000000000011 $!
0%!
#35
0"
07
0@
0I
0R
0[
0d
0m
0v
0!!
#40
1"
1$
0&
0'
b00000000000000000000000000000010 -
17
b0000000000000011 9
b0000000000000100 :
1@
1A
b0000000000000001 B
b0000000000000010 C
1D
0E
1G
1I
b0000000000000011 K
b0000000000000100 L
1N
1O
1R
0S
b0000000000000011 T
b0000000000000100 U
0X
0Y
1[
0\
b0000000000000011 ]
b0000000000000100 ^
0a
0b
1d
b0000000000000011 f
b0000000000000100 g
1j
1k
1m
b0000000000000011 o
b0000000000000100 p
1s
1t
1v
b0000000000000011 x
b0000000000000100 y
1!!
b0000000000000011 #!
b0000000000000100 $!
#45
0"
07
0@
0I
0R
0[
0d
0m
0v
0!!
#50
1"
0$
1%
0(
0)
b00000000000000000000000000000010 .
17
b0000000000000100 9
b0000000000000101 :
1@
0A
b0000000000000010 B
b0000000000000011 C
0D
1E
0G
1I
1J
b0000000000000001 K
b0000000000000010 L
1M
0N
1P
1R
b0000000000000100 T
b0000000000000101 U
1W
1X
1[
b0000000000000100 ]
b0000000000000101 ^
1d
0e
b0000000000000100 f
b0000000000000101 g
0j
0k
1m
0n
b0000000000000100 o
b0000000000000101 p
0s
0t
1v
b0000000000000100 x
b0000000000000101 y
1|
1}
1!!
b0000000000000100 #!
b0000000000000101 $!
1'!
1(!
#55
0"
07
0@
0I
0R
0[
0d
0m
0v
0!!
#60
1"
1$
0%
1&
0*
0+
b00000000000000000000000000000011 -
b00000000000000000000000000000010 /
17
b0000000000000101 9
b0000000000000110 :
1=
1>
1@
1A
b0000000000000001 B
b0000000000000010 C
1D
0E
1G
1I
0J
b0000000000000010 K
b0000000000000011 L
0M
0O
0P
1R
1S
b0000000000000001 T
b0000000000000010 U
1V
0W
0X
1[
b0000000000000101 ]
b0000000000000110 ^
1`
1a
1d
b0000000000000101 f
b0000000000000110 g
1m
b0000000000000101 o
b0000000000000110 p
1v
0w
b0000000000000101 x
b0000000000000110 y
0|
0}
1!!
0"!
b0000000000000101 #!
b0000000000000110 $!
0'!
0(!
#65
0"
07
0@
0I
0R
0[
0d
0m
0v
0!!
#70
1"
0$
1'
0,
b00000000000000000000000000000010 0
17
08
b0000000000000110 9
b0000000000000111 :
0=
0>
1@
0A
b0000000000000010 B
b0000000000000011 C
0D
1E
0G
1I
b0000000000000011 K
b0000000000000100 L
1N
1O
1R
b0000000000000010 T
b0000000000000011 U
0V
1X
1Y
1[
1\
b0000000000000001 ]
b0000000000000010 ^
1_
0`
0a
1d
b0000000000000110 f
b0000000000000111 g
1i
1j
1m
b0000000000000110 o
b0000000000000111 p
1v
b0000000000000110 x
b0000000000000111 y
1!!
b0000000000000110 #!
b0000000000000111 $!
#75
0"
07
0@
0I
0R
0[
0d
0m
0v
0!!
#80
1"
1$
1%
0&
1(
b00000000000000000000000000000100 -
b00000000000000000000000000000011 .
b00000000000000000000000000000010 1
17
b0000000000000111 9
b0000000000001000 :
1@
1A
b0000000000000001 B
b0000000000000010 C
1D
0E
1G
1I
1J
b0000000000000001 K
b0000000000000010 L
1M
0N
1P
1R
0S
b0000000000000011 T
b0000000000000100 U
0X
0Y
1[
b0000000000000010 ]
b0000000000000011 ^
0_
1a
1b
1d
1e
b0000000000000001 f
b0000000000000010 g
1h
0i
0j
1m
b0000000000000111 o
b0000000000001000 p
1r
1s
1v
b0000000000000111 x
b0000000000001000 y
1!!
b0000000000000111 #!
b0000000000001000 $!
#85
0"
07
0@
0I
0R
0[
0d
0m
0v
0!!
