modules/consts.vh
/*
    Constants definitions
*/
`define DEBUG_RUN 1             // uncomment to see some debug messages
`define GATE_FLOW 1             // uncomment to use gate flow logic (should be uncommented by default)
//`define CONST_DELAYS_OFF      // uncomment to disable delays in combinational and sequential logic

`ifndef CONST_DELAYS_OFF
    `define T_DELAY_FF 2
    `define T_DELAY_PD 1
`else
    `define T_DELAY_FF 0
    `define T_DELAY_PD 0
`endif

modules/adder.v
/*
    FULL ADDERs and HALF ADDERs

For unsigned addtition if sum is bigger than bits size, then carry bit will rise!
For signed addition or substraction MSB is the sign bit, but if sum is bigger than bits number,
then overflow will rise and the carry bit will hold the sign fo the sum!
Then, a program instruction that specifies unsigned operands can use the carry-out signal,
while an instruction that has signed operands can use the overflow signal.
*/
/* verilator lint_off DECLFILENAME */
/* verilator lint_off MULTITOP */
/* verilator lint_off GENUNNAMED */
`include "consts.vh"


/*
    N bit FULL ADDER and Comparator - max delay is N bits * FA delay (N*3 gates)

f="adder"; m="adder"
yosys -p "read_verilog ${f}.v; hierarchy -check -top $m; proc; techmap; clean; opt; clean -purge; stat; write_verilog -noattr synth/${m}_synth.v; show -format svg -prefix synth/${m} ${m}; show ${m}"
*/
module adder #(parameter n = 4) (
    input Nadd_sub,             // Mode select: 0 = addition; 1 = substraction
    input [n-1:0] X,
    input [n-1:0] Y,
    output wire [n-1:0] sum,
    output wire carry,
    output wire overflow,
    output wire eq,
    output wire lt,
    output wire ltu
);
    wire same_sign, cmp;

    `ifdef GATE_FLOW
        // ripple carry adder
        wire [n:0] C;
        genvar k;

        assign C[0] = Nadd_sub;

        generate
            for (k = 0; k < n; k = k + 1) begin
                full_adder fa_k (.a(X[k]), .b(Y[k] ^ Nadd_sub), .cin(C[k]), .sum(sum[k]), .carry(C[k+1]));
            end
        endgenerate
    `else
        // Fast adder. Predicting carry using the generation function of x[k] & y[k]
        reg [n:0] C;
        reg [n-1:0] y2c, s;
        integer k;

        assign sum = s;

        always @(*) begin
            C[0] = Nadd_sub;
            for (k = 0; k < n; k = k + 1) begin
                y2c[k] = Y[k] ^ Nadd_sub;
                s[k] = X[k] ^ y2c[k] ^ C[k];
                C[k + 1] = (X[k] & y2c[k]) | ((X[k] + y2c[k]) & C[k]);
            end
        end
    `endif

    assign same_sign = X[n-1] ^ Y[n-1];
    assign carry = C[n];
    assign overflow = C[n-1] ^ C[n];        // alternative: X[n-1] & Y[n-1] & ~sum[n-1];
    assign eq = Nadd_sub & ~(|sum);         // Equality
    assign cmp = Nadd_sub & ~eq;
    assign ltu = cmp & ~carry;   // Less Than unsigned. alternative: ~sum[n-1];
    assign lt = cmp & ((~same_sign & ~carry) | (same_sign & carry)); // Less Than signed
endmodule


/*
N bit FULL ADDER (ripple carry)

f="adder_full_n"
m="adder_full_n"
yosys -p "read_verilog ${f}.v; hierarchy -check -top $m; proc; flatten; techmap; clean; splitnets -ports; opt; clean -purge; stat; write_verilog -noattr synth/${m}_synth.v; show -format svg -prefix synth/${m} ${m}; show ${m}"
*/
module adder_full_n #(parameter n = 4) (
    input [n-1:0] X,
    input [n-1:0] Y,
    input Cin,
    output reg [n-1:0] sum,
    output reg carry
);
    reg [n:0] C;
    integer k;

    always @(X, Y, Cin) begin
        C[0] = Cin;
        for (k = 0; k < n; k = k + 1) begin
            sum[k] = X[k] ^ Y[k] ^ C[k];
            C[k + 1] = (X[k] & Y[k]) | (X[k] & C[k]) | (Y[k] & C[k]);
        end
        carry = C[n];
    end
endmodule


/*
Full Adder: max delay is for carry - 3 gates

f="adder"; m="full_adder"
yosys -p "read_verilog ${f}.v; hierarchy -check -top $m; proc; techmap; clean; stat; write_verilog -noattr synth/${m}_synth.v; show -format svg -prefix synth/${m} ${m}; show ${m}"
*/
module full_adder (
    input a,
    input b,
    input cin,
    output wire sum,
    output wire carry
);
    `ifdef GATE_FLOW
        wire sum1, c1, c2;
        half_adder h0(.a(a), .b(b), .sum(sum1), .carry(c1));
        half_adder h1(.a(sum1), .b(cin), .sum(sum), .carry(c2));
        or #(`T_DELAY_PD) o1(carry, c1, c2);
    `else
        assign sum = a ^ b ^ cin;
        assign carry = (a & b) | (a & cin) | (b & cin);
    `endif
endmodule


/*
Half Adder: 1 gate delay

f="adder"; m="half_adder"
yosys -p "read_verilog ${f}.v; hierarchy -check -top $m; proc; techmap; clean; stat; write_verilog -noattr synth/${m}_synth.v; show -format svg -prefix synth/${m} ${m}; show ${m}"
*/
module half_adder (
    input a,
    input b,
    output wire sum,
    output wire carry
);
    `ifdef GATE_FLOW
        and #(`T_DELAY_PD) (carry, a, b);
        xor #(`T_DELAY_PD) (sum, a, b);
    `else
        assign carry = a & b;
        assign sum = a ^ b;
    `endif
endmodule

modules/testbench/adder_tb.v
/* 
    Full adder and comparator testbench
*/
`include "consts.vh"
`timescale 1ns / 100ps
`define VCD "vcd/adder_tb.vcd"


module adder_tb();
    localparam n = 4;
    localparam T_DELAY = `T_DELAY_PD * 3 * n;

    wire [n-1:0] sum;
    wire carry, of, eq, lt, ltu;
    reg [n-1:0] X, Y;
    reg mode, msb;
    reg signed [n:0] sum_s;

    integer j, q, check_c, check_s;

    adder #(.n(n)) UUT (.X(X), .Y(Y), .Nadd_sub(mode), .sum(sum), .carry(carry), .overflow(of), .eq(eq), .lt(lt), .ltu(ltu));

    task check_values;
        input [n-1:0] ex_sum;
        input ex_carry;
        input ex_overflow;
        input ex_eq;
        input ex_lt;
        input ex_ltu;
    begin
        #T_DELAY if (of)
            msb = carry;
        else
            msb = sum[n-1];
        sum_s = $signed({msb, sum});
        $display("%8d INFO: X=%4b Y=%4b Nadd_sub=%b: sum=%4d (%4b with sign %0b) overflow=%0b, carry=%0d, eq=%0b, lt=%0b, ltu=%0b", $time, X, Y, mode, sum_s, sum, msb, of, carry, eq, lt, ltu);
        if (sum !== ex_sum)
            $display("*** ERROR: sum %0d (%0b) is not equal to expected %0d", sum, sum, ex_sum);
        if (carry != ex_carry)
            $display("*** ERROR: carry %0b is not equal to expected %0b", carry, ex_carry);
        if (of != ex_overflow)
            $display("*** ERROR: overflow %0b is not equal to expected %0b", of, ex_overflow);
        if (eq != ex_eq)
            $display("*** ERROR: eq %0b is not equal to expected %0b", of, ex_eq);
        if (lt != ex_lt)
            $display("*** ERROR: lt %0b is not equal to expected %0b", of, ex_lt);
        if (ltu != ex_ltu)
            $display("*** ERROR: ltu %0b is not equal to expected %0b", of, ex_ltu);
    end
    endtask

    initial begin
        $dumpfile(`VCD);
        $dumpvars();

        // Per stage test
        for (j = 0; j < n; j = j + 1) begin

            $display("Test stuck at 1's");
            X = 0; Y = 0; mode = 0;
            check_values(0, 0, 0, 1'bX, 1'bX, 1'bX);

            $display("Test per stage %0d. q is per stage inputs X, Y. Checking each FA bit by bit.", j);
            for (q = 1; q < 2**n - 1; q = q + 1) begin
                if (j == 0)
                    {X[j], Y[j]} = q[1:0];
                else begin
                    Y[j-1] = 1'b1;
                    {X[j-1], X[j], Y[j]} = q;
                end
                check_s = X + Y;
                check_c = check_s > 2**n - 1;
                check_s = check_s[n-1:0];
                check_values(check_s, check_c, 1'bX, 1'bX, 1'bX, 1'bX);
            end
        end

        $display("Test crosstalk");
        X = 2**n - 1; Y = 2**n - 1; mode = 0;
        check_values(2**n - 2, 1, 0, 1'bX, 1'bX, 1'bX);

        X = -1; Y = -1; mode = 0;
        check_values(-2, 1, 0, 1'bX, 1'bX, 1'bX);

        $display("Test substraction: N bits represent values 2**%0d/2...-2**%0d/2+1", n, n);
        $display("Checking all cases as signed numbers");
        $display("So we have only N-1 bits to represent magnitude");
        $display("If overflow=1: then sign is the carry");
        $display("If overflow=0: then sign is the MSB (Sn-1) and carry ignored");
        $display("For substarction: not checking carry if overflow");
        
        X = -7; Y = -2; mode = 0;
        check_values(-9, 1'b1, 1'b1, 1'bX, 1'bX, 1'bX);

        X = 0; Y = 1; mode = 1;
        check_values(-1, 1'bX, 1'b0, 0, 1, 1);

        X = 2**n - 1; Y = 1; mode = 1;
        check_values(-2, 1'bX, 1'b0, 0, 1, 0);

        X = -1; Y = 1; mode = 1;
        check_values(-2, 1'bX, 1'b0, 0, 1, 0);

        X = 2**n - 1; Y = 2**n - 1; mode = 1;
        check_values(0, 1'bX, 1'b0, 1, 0, 0);

        X = 0; Y = 2**n - 1; mode = 1;
        check_values(1, 1'bX, 1'b0, 0, 0, 1);

        $display("Test comparator");
        $display("Same sign for both, X > Y: expect carry 1:");
        X = 4; Y = 3; mode = 1;
        check_values(1, 1'b1, 1'b0, 0, 0, 0);

        X = -3; Y = -4; mode = 1;
        check_values(1, 1'b1, 1'b0, 0, 0, 0);

        $display("Same sign for both, X < Y: expect carry 0:");
        X = 3; Y = 4; mode = 1;
        check_values(-1, 1'b0, 1'b0, 0, 1, 1);

        X = -4; Y = -3; mode = 1;
        check_values(-1, 1'b0, 1'b0, 0, 1, 1);

        $display("Different signs: X > Y: expect carry 0");
        X = 4; Y = -3; mode = 1;
        check_values(7, 1'b0, 1'b0, 0, 0, 1);

        X = 3; Y = -4; mode = 1;
        check_values(7, 1'b0, 1'b0, 0, 0, 1);

        $display("Different signs: X < Y: expect carry 1");
        X = -4; Y = 3; mode = 1;
        check_values(-7, 1'b1, 1'b0, 0, 1, 0);

        X = -3; Y = 4; mode = 1;
        check_values(-7, 1'b1, 1'b0, 0, 1, 0);

        $display("Test comparator with overflow (should be same)");
        $display("Different signs: X > Y: expect carry 0");
        X = 4; Y = -5; mode = 1;
        check_values(9, 1'b0, 1'b1, 0, 0, 1);

        X = 6; Y = -5; mode = 1;
        check_values(11, 1'b0, 1'b1, 0, 0, 1);

        $display("Different signs: X < Y: expect carry 1");
        X = -5; Y = 7; mode = 1;
        check_values(-12, 1'b1, 1'b1, 0, 1, 0);

        X = -7; Y = 3; mode = 1;
        check_values(-10, 1'b1, 1'b1, 0, 1, 0);

        $display("End of testbench: %s", `VCD);
        $finish;
    end
endmodule

modules/vcd/adder_tb.vcd
$date
	Fri Jan 23 14:52:29 2026
$end
$version
	Icarus Verilog
$end
$timescale
	100ps
$end
$scope module adder_tb $end
$var wire 4 ! sum [3:0] $end
$var wire 1 " of $end
$var wire 1 # ltu $end
$var wire 1 $ lt $end
$var wire 1 % eq $end
$var wire 1 & carry $end
$var real 1 ' T_DELAY $end
$var parameter 32 ( n $end
$var reg 4 ) X [3:0] $end
$var reg 4 * Y [3:0] $end
$var reg 1 + mode $end
$var reg 1 , msb $end
$var reg 5 - sum_s [4:0] $end
$var integer 32 . check_c [31:0] $end
$var integer 32 / check_s [31:0] $end
$var integer 32 0 j [31:0] $end
$var integer 32 1 q [31:0] $end
$scope module UUT $end
$var wire 1 + Nadd_sub $end
$var wire 4 2 X [3:0] $end
$var wire 4 3 Y [3:0] $end
$var wire 1 4 cmp $end
$var wire 1 % eq $end
$var wire 1 $ lt $end
$var wire 1 # ltu $end
$var wire 1 " overflow $end
$var wire 1 5 same_sign $end
$var wire 4 6 sum [3:0] $end
$var wire 1 & carry $end
$var parameter 32 7 n $end
$var reg 5 8 C [4:0] $end
$var reg 4 9 s [3:0] $end
$var reg 4 : y2c [3:0] $end
$var integer 32 ; k [31:0] $end
$upscope $end
$scope task check_values $end
$var reg 1 < ex_carry $end
$var reg 1 = ex_eq $end
$var reg 1 > ex_lt $end
$var reg 1 ? ex_ltu $end
$var reg 1 @ ex_overflow $end
$var reg 4 A ex_sum [3:0] $end
$upscope $end
$upscope $end
$enddefinitions $end
$comment Show the parameter values. $end
$dumpall
b100 7
b100 (
r9.600000000000001 '
$end
#0
$dumpvars
b0 A
0@
x?
x>
x=
0<
b100 ;
b0 :
b0 9
b0 8
b0 6
05
04
b0 3
b0 2
bx 1
b0 0
bx /
bx .
bx -
x,
0+
b0 *
b0 )
0&
0%
0$
0#
0"
b0 !
$end
#96
b1 !
b1 6
b1 9
b1 :
b100 ;
x@
b1 A
b0 .
b1 /
b1 *
b1 3
b1 1
b0 -
0,
#192
b0 :
b100 ;
b1 )
b1 2
b0 *
b0 3
b10 1
b1 -
#288
b10 8
b10 !
b10 6
b10 9
b1 :
b100 ;
b10 A
b10 /
b1 *
b1 3
b11 1
#384
b0 !
b0 6
b0 9
b0 8
b0 :
b100 ;
b0 A
b0 /
b0 )
b0 2
b0 *
b0 3
b100 1
b10 -
#480
b1 !
b1 6
b1 9
b1 :
b100 ;
b1 A
b1 /
b1 *
b1 3
b101 1
b0 -
#576
b0 :
b100 ;
b1 )
b1 2
b0 *
b0 3
b110 1
b1 -
#672
b10 8
b10 !
b10 6
b10 9
b1 :
b100 ;
b10 A
b10 /
b1 *
b1 3
b111 1
#768
b0 !
b0 6
b0 9
b0 8
b0 :
b100 ;
b0 A
b0 /
b0 )
b0 2
b0 *
b0 3
b1000 1
b10 -
#864
b1 !
b1 6
b1 9
b1 :
b100 ;
b1 A
b1 /
b1 *
b1 3
b1001 1
b0 -
#960
b0 :
b100 ;
b1 )
b1 2
b0 *
b0 3
b1010 1
b1 -
#1056
b10 8
b10 !
b10 6
b10 9
b1 :
b100 ;
b10 A
b10 /
b1 *
b1 3
b1011 1
#1152
b0 !
b0 6
b0 9
b0 8
b0 :
b100 ;
b0 A
b0 /
b0 )
b0 2
b0 *
b0 3
b1100 1
b10 -
#1248
b1 !
b1 6
b1 9
b1 :
b100 ;
b1 A
b1 /
b1 *
b1 3
b1101 1
b0 -
#1344
b0 :
b100 ;
b1 )
b1 2
b0 *
b0 3
b1110 1
b1 -
#1440
b0 !
b0 6
b0 9
b100 ;
0@
b0 A
b0 )
b0 2
b1 0
b1111 1
#1536
b11 !
b11 6
b11 9
b11 :
b100 ;
x@
b11 A
b11 /
b11 *
b11 3
b1 1
b0 -
#1632
b1 :
b100 ;
b10 )
b10 2
b1 *
b1 3
b10 1
b11 -
#1728
b100 8
b101 !
b101 6
b101 9
b11 :
b100 ;
b101 A
b101 /
b11 *
b11 3
b11 1
#1824
b1 :
b10 8
b10 !
b10 6
b10 9
b100 ;
b10 A
b10 /
b1 )
b1 2
b1 *
b1 3
b100 1
b101 -
#1920
b110 8
b100 !
b100 6
b100 9
b11 :
b100 ;
b100 A
b100 /
b11 *
b11 3
b101 1
b10 -
#2016
b1 :
b100 ;
b11 )
b11 2
b1 *
b1 3
b110 1
b100 -
#2112
b110 !
b110 6
b110 9
b11 :
b100 ;
b110 A
b110 /
b11 *
b11 3
b111 1
#2208
b1 :
b0 8
b1 !
b1 6
b1 9
b100 ;
b1 A
b1 /
b0 )
b0 2
b1 *
b1 3
b1000 1
b110 -
#2304
b11 !
b11 6
b11 9
b11 :
b100 ;
b11 A
b11 /
b11 *
b11 3
b1001 1
b1 -
#2400
b1 :
b100 ;
b10 )
b10 2
b1 *
b1 3
b1010 1
b11 -
#2496
b100 8
b101 !
b101 6
b101 9
b11 :
b100 ;
b101 A
b101 /
b11 *
b11 3
b1011 1
#2592
b1 :
b10 8
b10 !
b10 6
b10 9
b100 ;
b10 A
b10 /
b1 )
b1 2
b1 *
b1 3
b1100 1
b101 -
#2688
b110 8
b100 !
b100 6
b100 9
b11 :
b100 ;
b100 A
b100 /
b11 *
b11 3
b1101 1
b10 -
#2784
b1 :
b100 ;
b11 )
b11 2
b1 *
b1 3
b1110 1
b100 -
#2880
b0 !
b0 6
b0 9
b0 8
b0 :
b100 ;
0@
b0 A
b0 *
b0 3
b0 )
b0 2
b10 0
b1111 1
#2976
b110 !
b110 6
b110 9
b110 :
b100 ;
x@
b110 A
b110 /
b110 *
b110 3
b1 1
b0 -
#3072
b10 :
b100 ;
b100 )
b100 2
b10 *
b10 3
b10 1
b110 -
#3168
1"
b1000 8
b1010 !
b1010 6
b1010 9
b110 :
b100 ;
b1010 A
b1010 /
b110 *
b110 3
b11 1
#3264
0"
b10 :
b100 8
b100 !
b100 6
b100 9
b100 ;
b100 A
b100 /
b10 )
b10 2
b10 *
b10 3
b100 1
b1010 -
#3360
1"
b1100 8
b1000 !
b1000 6
b1000 9
b110 :
b100 ;
b1000 A
b1000 /
b110 *
b110 3
b101 1
b100 -
#3456
b10 :
b100 ;
b110 )
b110 2
b10 *
b10 3
b110 1
b1000 -
#3552
b1100 !
b1100 6
b1100 9
b110 :
b100 ;
b1100 A
b1100 /
b110 *
b110 3
b111 1
#3648
0"
b10 :
b0 8
b10 !
b10 6
b10 9
b100 ;
b10 A
b10 /
b0 )
b0 2
b10 *
b10 3
b1000 1
b1100 -
#3744
b110 !
b110 6
b110 9
b110 :
b100 ;
b110 A
b110 /
b110 *
b110 3
b1001 1
b10 -
#3840
b10 :
b100 ;
b100 )
b100 2
b10 *
b10 3
b1010 1
b110 -
#3936
1"
b1000 8
b1010 !
b1010 6
b1010 9
b110 :
b100 ;
b1010 A
b1010 /
b110 *
b110 3
b1011 1
#4032
0"
b10 :
b100 8
b100 !
b100 6
b100 9
b100 ;
b100 A
b100 /
b10 )
b10 2
b10 *
b10 3
b1100 1
b1010 -
#4128
1"
b1100 8
b1000 !
b1000 6
b1000 9
b110 :
b100 ;
b1000 A
b1000 /
b110 *
b110 3
b1101 1
b100 -
#4224
b10 :
b100 ;
b110 )
b110 2
b10 *
b10 3
b1110 1
b1000 -
#4320
0"
b0 !
b0 6
b0 9
b0 8
b0 :
b100 ;
0@
b0 A
b0 *
b0 3
b0 )
b0 2
b11 0
b1111 1
#4416
15
b1100 !
b1100 6
b1100 9
b1100 :
b100 ;
x@
b1100 A
b1100 /
b1100 *
b1100 3
b1 1
b0 -
#4512
b100 :
b100 ;
b1000 )
b1000 2
b100 *
b100 3
b10 1
b11100 -
1,
#4608
1"
1&
05
b10000 8
b100 !
b100 6
b100 9
b1100 :
b100 ;
1<
b100 A
b1 .
b100 /
b1100 *
b1100 3
b11 1
#4704
0&
b100 :
b1000 8
b1000 !
b1000 6
b1000 9
b100 ;
0<
b1000 A
b0 .
b1000 /
b100 )
b100 2
b100 *
b100 3
b100 1
b10100 -
#4800
0"
1&
15
b11000 8
b0 !
b0 6
b0 9
b1100 :
b100 ;
1<
b0 A
b1 .
b0 /
b1100 *
b1100 3
b101 1
b1000 -
0,
#4896
b100 :
b100 ;
b0 /
b1100 )
b1100 2
b100 *
b100 3
b110 1
b0 -
#4992
05
b1000 !
b1000 6
b1000 9
b1100 :
b100 ;
b1000 A
b1000 /
b1100 *
b1100 3
b111 1
#5088
0&
b100 :
b0 8
b100 !
b100 6
b100 9
b100 ;
0<
b100 A
b0 .
b100 /
b0 )
b0 2
b100 *
b100 3
b1000 1
b11000 -
1,
#5184
15
b1100 !
b1100 6
b1100 9
b1100 :
b100 ;
b1100 A
b1100 /
b1100 *
b1100 3
b1001 1
b100 -
0,
#5280
b100 :
b100 ;
b1000 )
b1000 2
b100 *
b100 3
b1010 1
b11100 -
1,
#5376
1"
1&
05
b10000 8
b100 !
b100 6
b100 9
b1100 :
b100 ;
1<
b100 A
b1 .
b100 /
b1100 *
b1100 3
b1011 1
#5472
0&
b100 :
b1000 8
b1000 !
b1000 6
b1000 9
b100 ;
0<
b1000 A
b0 .
b1000 /
b100 )
b100 2
b100 *
b100 3
b1100 1
b10100 -
#5568
0"
1&
15
b11000 8
b0 !
b0 6
b0 9
b1100 :
b100 ;
1<
b0 A
b1 .
b0 /
b1100 *
b1100 3
b1101 1
b1000 -
0,
#5664
b100 :
b100 ;
b0 /
b1100 )
b1100 2
b100 *
b100 3
b1110 1
b0 -
#5760
05
b1110 !
b1110 6
b1110 9
b11110 8
b1111 :
b100 ;
0@
b1110 A
b1111 *
b1111 3
b1111 )
b1111 2
b100 0
b1111 1
#5856
b11110 -
1,
#5952
1"
b10000 8
b111 !
b111 6
b111 9
b1110 :
b100 ;
1@
b111 A
b1110 *
b1110 3
b1001 )
b1001 2
#6048
1$
1#
0"
0&
14
b1111 !
b1111 6
b1111 9
b100 ;
b1 8
1?
1>
0=
0@
x<
b1111 A
1+
b1 *
b1 3
b0 )
b0 2
b10111 -
#6144
0#
1&
15
b11111 8
b1110 !
b1110 6
b1110 9
b100 ;
0?
b1110 A
b1111 )
b1111 2
b11111 -
#6240
b11110 -
#6336
04
0$
1%
05
b0 !
b0 6
b0 9
b0 :
b100 ;
0>
1=
b0 A
b1111 *
b1111 3
#6432
1#
14
0%
0&
15
b1 8
b1 !
b1 6
b1 9
b100 ;
1?
0=
b1 A
b0 )
b0 2
b0 -
0,
#6528
0#
05
1&
b11001 8
b1100 :
b100 ;
0?
1<
b11 *
b11 3
b100 )
b100 2
b1 -
#6624
b11111 8
b11 :
b100 ;
b1100 *
b1100 3
b1101 )
b1101 2
#6720
1$
1#
0&
b1011 :
b111 8
b1111 !
b1111 6
b1111 9
b100 ;
1?
1>
0<
b1111 A
b100 *
b100 3
b11 )
b11 2
#6816
b1 8
b10 :
b100 ;
b1101 *
b1101 3
b1100 )
b1100 2
b11111 -
1,
#6912
0$
15
b111 !
b111 6
b111 9
b100 ;
0>
b111 A
b100 )
b100 2
#7008
b111 8
b11 :
b100 ;
b1100 *
b1100 3
b11 )
b11 2
b111 -
0,
#7104
1$
0#
1&
b1001 !
b1001 6
b1001 9
b11001 8
b1100 :
b100 ;
0?
1>
1<
b1001 A
b11 *
b11 3
b1100 )
b1100 2
#7200
b11111 8
b1011 :
b100 ;
b100 *
b100 3
b1101 )
b1101 2
b11001 -
1,
#7296
0$
1#
1"
0&
b1001 8
b100 :
b100 ;
1?
0>
1@
0<
b1011 *
b1011 3
b100 )
b100 2
#7392
b1011 !
b1011 6
b1011 9
b100 ;
b1011 A
b110 )
b110 2
b1001 -
0,
#7488
1$
0#
1&
b1000 :
b10111 8
b100 !
b100 6
b100 9
b100 ;
0?
1>
1<
b100 A
b111 *
b111 3
b1011 )
b1011 2
b1011 -
#7584
b1100 :
b10011 8
b110 !
b110 6
b110 9
b100 ;
b110 A
b11 *
b11 3
b1001 )
b1001 2
b10100 -
1,
#7680
b10110 -
