modules/sequence.v
/*
    4 bit sequence detector with async reset and overlapping
*/
/* verilator lint_off DECLFILENAME */
/* verilator lint_off MULTITOP */
/* verilator lint_off GENUNNAMED */
`timescale 1ns / 1ns

/*
    m="sequence_detector"
    yosys -p "read_verilog sequence.v; hierarchy -check -top ${m}; proc; blackbox return_states; opt -nodffe -nosdff; clean; opt_share; opt_muxtree; clean; fsm_detect -ignore-self-reset; fsm; stat; write_verilog -noattr synth/${m}_synth.v; show -format svg -prefix synth/${m}; show"
    yosys -p "read_verilog sequence.v; hierarchy -check -top ${m}; proc; blackbox return_states; opt -nodffe -nosdff; clean; opt_share; opt_muxtree; clean; fsm_detect -ignore-self-reset; fsm -nomap; fsm_export -o ${m}.kiss2;"
    python3 kiss2dot.py ${m}_fsm.kiss2 > ${m}_fsm.dot; xdot ${m}_fsm.dot
*/
module sequence_detector #(parameter OVERLAP = 1) (
    input clk,
    input res_n,
    input [3:0] seq,
    input din,
    output reg dout
);
    localparam S0 = 2'b00;
    localparam S1 = 2'b01;
    localparam S2 = 2'b10;
    localparam S3 = 2'b11;
    wire [1:0] r1, r2, r3, c3;
    (* fsm_encoding = "auto" *) reg [1:0] state;
    reg [1:0] next_state;
    
    if (OVERLAP)
        // define overlapping states per current sequence
        return_states rs (.seq(seq), .r1(r1), .r2(r2), .r3(r3), .s3(c3));
    else begin
        // if din matches the first seq bit then we should move to S1
        assign r1 = din === seq[3] ? S1 : S0;
        assign r2 = din === seq[3] ? S1 : S0;
        assign r3 = din === seq[3] ? S1 : S0;
        assign c3 = S0;
    end

    // State update. Reset is async. Dout is sync.
    always @(posedge clk or negedge res_n) begin
        if (!res_n) begin
            state <= S0;
            dout <= 0;
        end else begin
            state <= next_state;
            dout <= (state == S3 && din === seq[0]) ? 1'b1 : 1'b0;
        end
    end

    always @(*) begin
        case (state)
            S0:
                next_state = din === seq[3] ? S1 : S0;
            S1:
                next_state = din === seq[2] ? S2 : r1;
            S2:
                next_state = din === seq[1] ? S3 : r2;
            S3:
                next_state = din === seq[0] ? c3 : r3;
            default:
                next_state = S0;
        endcase
    end
endmodule


/*
    Define return states for overlapping patterns

    m="return_states"
    yosys -p "read_verilog sequence.v; hierarchy -check -top ${m}; proc; opt -nodffe -nosdff; clean; opt_share; opt_muxtree; techmap; clean; stat; write_verilog -noattr synth/sequence_detector_${m}_synth.v; show -format svg -prefix synth/sequence_detector_${m}; show"
*/
module return_states(
    input [3:0] seq,
    output wire [1:0] r1,
    output wire [1:0] r2,
    output wire [1:0] r3,
    output wire [1:0] s3
);
    localparam S0 = 2'b00;
    localparam S1 = 2'b01;
    localparam S2 = 2'b10;
    localparam S3 = 2'b11;

    assign r1 = (seq[3] ^~ seq[2]) ? S0 : S1;
    assign r2 = (seq[3] ^~ seq[2] && seq[2] ^ seq[1]) ? S2 : (seq[3] ^ seq[1] ? S1 : S0);
    assign r3 = (seq[3] ^~ seq[2] && seq[2] ^~ seq[1] && seq[1] ^ seq[0]) ? S3 : ((seq[3] ^~ seq[1] && seq[1] ^~ seq[0] && seq[3] ^ seq[2]) ? S2 : (seq[3] ^ seq[0] ? S1 : S0));
    assign s3 = (seq[3] ^~ seq[2] && seq[2] ^~ seq[1] && seq[1] ^~ seq[0]) ? S3 : ((seq[3] ^~ seq[1] && seq[2] ^~ seq[0]) ? S2 : (seq[3] ^ seq[0] ? S0 : S1));
endmodule


/*
    Basic 1010 detector with overlapping

    f="sequence"; m="sequence_detector_1010"
    yosys -p "read_verilog sequence.v; hierarchy -check -top ${m}; proc; opt -nodffe -nosdff; clean; opt_share; opt_muxtree; clean; fsm_detect -ignore-self-reset; fsm -nomap; fsm_export -o ${m}_fsm.kiss2; stat; write_verilog -noattr synth/${m}_synth.v; show -format svg -prefix synth/${m}; show"
    python3 kiss2dot.py ${m}_fsm.kiss2 > ${m}_fsm.dot; xdot ${m}_fsm.dot

    add "simplemap;" after fsm step (without nomap) to see 2 DFFs
*/
module sequence_detector_1010 (
    input clk,
    input res_n,
    input din,
    output wire out
);
    parameter pass = 4'b1010;
    localparam S0 = 2'b00;
    localparam S1 = 2'b01;
    localparam S2 = 2'b10;
    localparam S3 = 2'b11;
    (* fsm_encoding = "binary" *) reg [1:0] state;
    reg [1:0] next_state;

    // State update. Reset is async.
    always @(posedge clk or negedge res_n) begin
        if (!res_n)
            state <= S0;
        else
            state <= next_state;
    end

    assign out = (state == S3 && din ^~ pass[0]) ? 1'b1 : 1'b0;

    always @(*) begin
        case (state)
            S0:
                next_state = din ^~ pass[3] ? S1 : S0;
            S1:
                next_state = din ^~ pass[2] ? S2 : S1;
            S2:
                next_state = din ^~ pass[1] ? S3 : S0;
            S3:
                next_state = din ^~ pass[0] ? S2 : S1;
            default:
                next_state = S0;
        endcase
    end
endmodule


/*
    optimized FSM's for 1010
*/
module sequence_detector_1010_mealy(
    input clk,
    input res_n,
    input din,
    output reg dout
);
    reg s2, s1;

    // DFF update. Reset is async.
    always @(posedge clk or negedge res_n) begin
        if (!res_n) begin
            s1 <= 0;
            s2 <= 0;
            dout <= 0;
        end else begin
            s1 <= din;
            s2 <= (din & s2 & ~s1) | (~din & s1);
            dout <= ~din & s2 & s1;
        end
    end
endmodule


module sequence_detector_1010_moore(
    input clk,
    input res_n,
    input din,
    output wire dout
);
    reg s2, s1, s3;

    assign dout = s3;

    // DFF update. Reset is async.
    always @(posedge clk or negedge res_n) begin
        if (!res_n) begin
            s1 <= 0;
            s2 <= 0;
            s3 <= 0;
        end else begin
            s1 <= din;
            s3 <= ~din & s1 & s2;
            s2 <= (~din & s1) | (din & ~s1 & (s2 | s3));
        end
    end
endmodule

modules/testbench/sequence_tb.v
`timescale 1ns / 1ns

`define VCD "vcd/sequence_tb.vcd"


module sequence_tb();
    reg clk, reset, data;
    reg [3:0] pass;
    wire out, out2;
    reg OUT;
    reg [31:0] stimulus;
    reg [31:0] result;
    localparam T_CLK = 10;
    localparam T_CYC = T_CLK * 2;
    integer tc_counter = 0;
    integer no_overlapp = 0;
    integer i, fn, expected;

    sequence_detector dut(.clk(clk), .res_n(reset), .seq(pass), .din(data), .dout(out));
    sequence_detector #(0) dut_no(.clk(clk), .res_n(reset), .seq(pass), .din(data), .dout(out2));

    always begin
        #T_CLK clk = ~clk;
        fn = $time / T_CYC;
        OUT = no_overlapp ? out2 : out;
        // each stimulus takes 34 clk phases: 32 bits + reset + post if
        result = result | OUT << (tc_counter * 34 - fn);
    end

    initial begin
        $dumpfile(`VCD);
        $dumpvars();
        $monitor("%0d: fn=%0d, d=%0d, out=%0d, result=%0b", $time, fn, data, OUT, result);

        clk = 1'b0;

        reset = 0;
        #T_CYC reset = 1;
        result = 0;
        tc_counter = tc_counter + 1;
        pass = 4'b1010;
        stimulus = 32'b01001011101001010110101110101011;
        expected = 32'b100001000010000010100;
        for (i = 32; i > 0; i = i - 1)
            #T_CYC data = stimulus[i - 1];
        #T_CYC if (result != expected)
            $display("%0d: TEST %0d FAILED: got %0b instead of %0b", $time, tc_counter, result, expected);
        else
            $display("%0d: TEST %0d PASSED", $time, tc_counter);

        reset = 0;
        #T_CYC reset = 1;
        result = 0;
        tc_counter = tc_counter + 1;
        pass = 4'b1101;
        stimulus = 32'b01001011101001010110101110110110;
        expected = 32'b1000000000100000100100;
        for (i = 32; i > 0; i = i - 1)
            #T_CYC data = stimulus[i - 1];
        #T_CYC if (result != expected)
            $display("%0d: TEST %0d FAILED: got %0b instead of %0b", $time, tc_counter, result, expected);
        else
            $display("%0d: TEST %0d PASSED", $time, tc_counter);

        reset = 0;
        #T_CYC reset = 1;
        result = 0;
        tc_counter = tc_counter + 1;
        pass = 4'b0110;
        stimulus = 32'b01001010100101011011011011011010;
        expected = 32'b100100100100100;
        for (i = 32; i > 0; i = i - 1)
            #T_CYC data = stimulus[i - 1];
        #T_CYC if (result != expected)
            $display("%0d: TEST %0d FAILED: got %0b instead of %0b", $time, tc_counter, result, expected);
        else
            $display("%0d: TEST %0d PASSED", $time, tc_counter);

        no_overlapp = 1;
        reset = 0;
        #T_CYC reset = 1;
        result = 0;
        tc_counter = tc_counter + 1;
        pass = 4'b0110;
        stimulus = 32'b01001010100101011011011011011010;
        expected = 32'b100000100000100;
        for (i = 32; i > 0; i = i - 1)
            #T_CYC data = stimulus[i - 1];
        #T_CYC if (result != expected)
            $display("%0d: TEST NON-OVERLAPPING %0d FAILED: got %0b instead of %0b", $time, tc_counter, result, expected);
        else
            $display("%0d: TEST NON-OVERLAPPING %0d PASSED", $time, tc_counter);

        reset = 0;
        #T_CYC reset = 1;
        result = 0;
        tc_counter = tc_counter + 1;
        pass = 4'b1101;
        stimulus = 32'b01001010100101011011011011011010;
        expected = 32'b10000010000010;
        for (i = 32; i > 0; i = i - 1)
            #T_CYC data = stimulus[i - 1];
        #T_CYC if (result != expected)
            $display("%0d: TEST NON-OVERLAPPING %0d FAILED: got %0b instead of %0b", $time, tc_counter, result, expected);
        else
            $display("%0d: TEST NON-OVERLAPPING %0d PASSED", $time, tc_counter);
        $display("End of testbench: %s", `VCD);
        $finish;
    end
endmodule

modules/vcd/sequence_tb.vcd
$date
	Mon Jan 19 10:02:48 2026
$end
$version
	Icarus Verilog
$end
$timescale
	1ns
$end
$scope module sequence_tb $end
$var wire 1 ! out2 $end
$var wire 1 " out $end
$var parameter 32 # T_CLK $end
$var parameter 64 $ T_CYC $end
$var reg 1 % OUT $end
$var reg 1 & clk $end
$var reg 1 ' data $end
$var reg 4 ( pass [3:0] $end
$var reg 1 ) reset $end
$var reg 32 * result [31:0] $end
$var reg 32 + stimulus [31:0] $end
$var integer 32 , expected [31:0] $end
$var integer 32 - fn [31:0] $end
$var integer 32 . i [31:0] $end
$var integer 32 / no_overlapp [31:0] $end
$var integer 32 0 tc_counter [31:0] $end
$scope module dut $end
$var wire 1 & clk $end
$var wire 1 ' din $end
$var wire 1 ) res_n $end
$var wire 4 1 seq [3:0] $end
$var wire 2 2 r3 [1:0] $end
$var wire 2 3 r2 [1:0] $end
$var wire 2 4 r1 [1:0] $end
$var wire 2 5 c3 [1:0] $end
$var parameter 32 6 OVERLAP $end
$var parameter 2 7 S0 $end
$var parameter 2 8 S1 $end
$var parameter 2 9 S2 $end
$var parameter 2 : S3 $end
$var reg 1 " dout $end
$var reg 2 ; next_state [1:0] $end
$var reg 2 < state [1:0] $end
$scope begin genblk1 $end
$scope module rs $end
$var wire 4 = seq [3:0] $end
$var wire 2 > s3 [1:0] $end
$var wire 2 ? r3 [1:0] $end
$var wire 2 @ r2 [1:0] $end
$var wire 2 A r1 [1:0] $end
$var parameter 2 B S0 $end
$var parameter 2 C S1 $end
$var parameter 2 D S2 $end
$var parameter 2 E S3 $end
$upscope $end
$upscope $end
$upscope $end
$scope module dut_no $end
$var wire 2 F c3 [1:0] $end
$var wire 1 & clk $end
$var wire 1 ' din $end
$var wire 1 ) res_n $end
$var wire 4 G seq [3:0] $end
$var wire 2 H r3 [1:0] $end
$var wire 2 I r2 [1:0] $end
$var wire 2 J r1 [1:0] $end
$var parameter 32 K OVERLAP $end
$var parameter 2 L S0 $end
$var parameter 2 M S1 $end
$var parameter 2 N S2 $end
$var parameter 2 O S3 $end
$var reg 1 ! dout $end
$var reg 2 P next_state [1:0] $end
$var reg 2 Q state [1:0] $end
$scope begin genblk1 $end
$upscope $end
$upscope $end
$upscope $end
$enddefinitions $end
$comment Show the parameter values. $end
$dumpall
b11 O
b10 N
b1 M
b0 L
b0 K
b11 E
b10 D
b1 C
b0 B
b11 :
b10 9
b1 8
b0 7
b1 6
b10100 $
b1010 #
$end
#0
$dumpvars
b0 Q
b1 P
b1 J
b1 I
b1 H
bx G
b0 F
b0x A
bx @
bx ?
bx >
bx =
b0 <
b1 ;
bx 5
b0x 4
bx 3
bx 2
bx 1
b0 0
b0 /
bx .
bx -
bx ,
bx +
bx *
0)
bx (
x'
0&
x%
0"
0!
$end
#10
0%
b0 -
1&
#20
b1 2
b1 ?
b0 3
b0 @
b10 5
b10 >
b1 4
b1 A
b0 J
b0 I
b0 H
b0 P
b0 ;
b1 -
0&
b100000 .
b100001000010000010100 ,
b1001011101001010110101110101011 +
b1010 (
b1010 1
b1010 =
b1010 G
b1 0
b0 *
1)
#30
1&
#40
b10 -
0&
b11111 .
0'
#50
1&
#60
b1 ;
b1 P
b1 J
b1 I
b1 H
b11 -
0&
b11110 .
1'
#70
b1 <
b1 Q
1&
#80
b10 ;
b10 P
b0 J
b0 I
b0 H
b100 -
0&
b11101 .
0'
#90
b0 P
b0 ;
b10 Q
b10 <
1&
#100
b101 -
0&
b11100 .
#110
b0 <
b0 Q
1&
#120
b1 ;
b1 P
b1 J
b1 I
b1 H
b110 -
0&
b11011 .
1'
#130
b1 Q
b1 <
1&
#140
b10 ;
b10 P
b0 J
b0 I
b0 H
b111 -
0&
b11010 .
0'
#150
b0 ;
b0 P
b10 <
b10 Q
1&
#160
b11 ;
b11 P
b1 J
b1 I
b1 H
b1000 -
0&
b11001 .
1'
#170
b1 P
b1 ;
b11 Q
b11 <
1&
#180
b1001 -
0&
b11000 .
#190
b1 <
b1 Q
1&
#200
b1010 -
0&
b10111 .
#210
1&
#220
b10 ;
b10 P
b0 J
b0 I
b0 H
b1011 -
0&
b10110 .
0'
#230
b0 ;
b0 P
b10 <
b10 Q
1&
#240
b11 ;
b11 P
b1 J
b1 I
b1 H
b1100 -
0&
b10101 .
1'
#250
b1 P
b1 ;
b11 Q
b11 <
1&
#260
b10 ;
b0 P
b0 J
b0 I
b0 H
b1101 -
0&
b10100 .
0'
#270
b0 ;
1"
b10 <
1!
b0 Q
1&
#280
b100000000000000000000 *
1%
b1110 -
0&
b10011 .
#290
0!
0"
b0 <
1&
#300
b1 ;
b1 P
b1 J
b1 I
b1 H
0%
b1111 -
0&
b10010 .
1'
#310
b1 <
b1 Q
1&
#320
b10 ;
b10 P
b0 J
b0 I
b0 H
b10000 -
0&
b10001 .
0'
#330
b0 P
b0 ;
b10 Q
b10 <
1&
#340
b11 ;
b11 P
b1 J
b1 I
b1 H
b10001 -
0&
b10000 .
1'
#350
b1 ;
b1 P
b11 <
b11 Q
1&
#360
b10 ;
b0 P
b0 J
b0 I
b0 H
b10010 -
0&
b1111 .
0'
#370
b0 ;
1!
b0 Q
1"
b10 <
1&
#380
b11 ;
b1 P
b1 J
b1 I
b1 H
b100001000000000000000 *
1%
b10011 -
0&
b1110 .
1'
#390
b1 ;
0"
b11 <
0!
b1 Q
1&
#400
0%
b10100 -
0&
b1101 .
#410
b1 <
1&
#420
b10 ;
b10 P
b0 J
b0 I
b0 H
b10101 -
0&
b1100 .
0'
#430
b0 ;
b0 P
b10 <
b10 Q
1&
#440
b11 ;
b11 P
b1 J
b1 I
b1 H
b10110 -
0&
b1011 .
1'
#450
b1 P
b1 ;
b11 Q
b11 <
1&
#460
b10 ;
b0 P
b0 J
b0 I
b0 H
b10111 -
0&
b1010 .
0'
#470
b0 ;
1"
b10 <
1!
b0 Q
1&
#480
b11 ;
b1 P
b1 J
b1 I
b1 H
b100001000010000000000 *
1%
b11000 -
0&
b1001 .
1'
#490
b1 ;
0!
b1 Q
0"
b11 <
1&
#500
0%
b11001 -
0&
b1000 .
#510
b1 <
1&
#520
b11010 -
0&
b111 .
#530
1&
#540
b10 ;
b10 P
b0 J
b0 I
b0 H
b11011 -
0&
b110 .
0'
#550
b0 ;
b0 P
b10 <
b10 Q
1&
#560
b11 ;
b11 P
b1 J
b1 I
b1 H
b11100 -
0&
b101 .
1'
#570
b1 P
b1 ;
b11 Q
b11 <
1&
#580
b10 ;
b0 P
b0 J
b0 I
b0 H
b11101 -
0&
b100 .
0'
#590
b0 ;
1"
b10 <
1!
b0 Q
1&
#600
b11 ;
b1 P
b1 J
b1 I
b1 H
b100001000010000010000 *
1%
b11110 -
0&
b11 .
1'
#610
b1 ;
0!
b1 Q
0"
b11 <
1&
#620
b10 ;
b10 P
b0 J
b0 I
b0 H
0%
b11111 -
0&
b10 .
0'
#630
b0 ;
b0 P
1"
b10 <
b10 Q
1&
#640
b11 ;
b11 P
b1 J
b1 I
b1 H
b100001000010000010100 *
1%
b100000 -
0&
b1 .
1'
#650
b1 P
b1 ;
b11 Q
0"
b11 <
1&
#660
0%
b100001 -
0&
b0 .
#670
b1 <
b1 Q
1&
#680
b0 Q
b0 <
b100010 -
0&
0)
#690
1&
#700
b0 2
b0 ?
b1 5
b1 >
b10 3
b10 @
b0 4
b0 A
b100011 -
0&
b100000 .
b1000000000100000100100 ,
b1001011101001010110101110110110 +
b1101 (
b1101 1
b1101 =
b1101 G
b10 0
b0 *
1)
#710
b10 P
b10 ;
b1 Q
b1 <
1&
#720
b0 ;
b0 P
b0 J
b0 I
b0 H
b100100 -
0&
b11111 .
0'
#730
b0 <
b0 Q
1&
#740
b1 ;
b1 P
b1 J
b1 I
b1 H
b100101 -
0&
b11110 .
1'
#750
b10 P
b10 ;
b1 Q
b1 <
1&
#760
b0 ;
b0 P
b0 J
b0 I
b0 H
b100110 -
0&
b11101 .
0'
#770
b0 <
b0 Q
1&
#780
b100111 -
0&
b11100 .
#790
1&
#800
b1 ;
b1 P
b1 J
b1 I
b1 H
b101000 -
0&
b11011 .
1'
#810
b10 ;
b10 P
b1 <
b1 Q
1&
#820
b0 ;
b0 P
b0 J
b0 I
b0 H
b101001 -
0&
b11010 .
0'
#830
b0 Q
b0 <
1&
#840
b1 ;
b1 P
b1 J
b1 I
b1 H
b101010 -
0&
b11001 .
1'
#850
b10 ;
b10 P
b1 <
b1 Q
1&
#860
b101011 -
0&
b11000 .
#870
b1 P
b10 Q
b10 <
1&
#880
b101100 -
0&
b10111 .
#890
b10 P
b1 Q
1&
#900
b11 ;
b0 P
b0 J
b0 I
b0 H
b101101 -
0&
b10110 .
0'
#910
b0 ;
b0 Q
b11 <
1&
#920
b1 ;
b1 P
b1 J
b1 I
b1 H
b101110 -
0&
b10101 .
1'
#930
b10 ;
b10 P
1"
b1 <
b1 Q
1&
#940
b0 ;
b0 P
b0 J
b0 I
b0 H
b1000000000000000000000 *
1%
b101111 -
0&
b10100 .
0'
#950
b0 Q
0"
b0 <
1&
#960
0%
b110000 -
0&
b10011 .
#970
1&
#980
b1 ;
b1 P
b1 J
b1 I
b1 H
b110001 -
0&
b10010 .
1'
#990
b10 P
b10 ;
b1 Q
b1 <
1&
#1000
b0 ;
b0 P
b0 J
b0 I
b0 H
b110010 -
0&
b10001 .
0'
#1010
b0 <
b0 Q
1&
#1020
b1 ;
b1 P
b1 J
b1 I
b1 H
b110011 -
0&
b10000 .
1'
#1030
b10 P
b10 ;
b1 Q
b1 <
1&
#1040
b0 ;
b0 P
b0 J
b0 I
b0 H
b110100 -
0&
b1111 .
0'
#1050
b0 <
b0 Q
1&
#1060
b1 ;
b1 P
b1 J
b1 I
b1 H
b110101 -
0&
b1110 .
1'
#1070
b10 P
b10 ;
b1 Q
b1 <
1&
#1080
b110110 -
0&
b1101 .
#1090
b1 P
b10 <
b10 Q
1&
#1100
b11 ;
b11 P
b0 J
b0 I
b0 H
b110111 -
0&
b1100 .
0'
#1110
b0 P
b0 ;
b11 Q
b11 <
1&
#1120
b1 ;
b1 J
b1 I
b1 H
b111000 -
0&
b1011 .
1'
#1130
b10 ;
b1 P
1"
b1 <
1!
b0 Q
1&
#1140
b0 ;
b0 P
b0 J
b0 I
b0 H
b1000000000100000000000 *
1%
b111001 -
0&
b1010 .
0'
#1150
0!
0"
b0 <
1&
#1160
b1 ;
b1 P
b1 J
b1 I
b1 H
0%
b111010 -
0&
b1001 .
1'
#1170
b10 ;
b10 P
b1 <
b1 Q
1&
#1180
b111011 -
0&
b1000 .
#1190
b1 P
b10 Q
b10 <
1&
#1200
b111100 -
0&
b111 .
#1210
b10 P
b1 Q
1&
#1220
b11 ;
b0 P
b0 J
b0 I
b0 H
b111101 -
0&
b110 .
0'
#1230
b0 ;
b0 Q
b11 <
1&
#1240
b1 ;
b1 P
b1 J
b1 I
b1 H
b111110 -
0&
b101 .
1'
#1250
b10 ;
b10 P
1"
b1 <
b1 Q
1&
#1260
b1000000000100000100000 *
1%
b111111 -
0&
b100 .
#1270
b1 P
b10 Q
0"
b10 <
1&
#1280
b11 ;
b11 P
b0 J
b0 I
b0 H
0%
b1000000 -
0&
b11 .
0'
#1290
b0 ;
b0 P
b11 <
b11 Q
1&
#1300
b1 ;
b1 J
b1 I
b1 H
b1000001 -
0&
b10 .
1'
#1310
b1 P
b10 ;
1!
b0 Q
1"
b1 <
1&
#1320
b1000000000100000100100 *
1%
b1000010 -
0&
b1 .
#1330
b10 P
0"
b10 <
0!
b1 Q
1&
#1340
b11 ;
b0 P
b0 J
b0 I
b0 H
0%
b1000011 -
0&
b0 .
0'
#1350
b0 ;
b0 Q
b11 <
1&
#1360
b0 <
b1000100 -
0&
0)
#1370
1&
#1380
b1 3
b1 @
b1 4
b1 A
b1 J
b1 I
b1 H
b1 P
b1 ;
b1000101 -
0&
b100000 .
b100100100100100 ,
b1001010100101011011011011011010 +
b110 (
b110 1
b110 =
b110 G
b11 0
b0 *
1)
#1390
b1 <
b1 Q
1&
#1400
b1000110 -
0&
b11111 .
#1410
1&
#1420
b10 ;
b10 P
b0 J
b0 I
b0 H
b1000111 -
0&
b11110 .
1'
#1430
b11 ;
b11 P
b10 <
b10 Q
1&
#1440
b1 ;
b1 P
b1 J
b1 I
b1 H
b1001000 -
0&
b11101 .
0'
#1450
b1 Q
b1 <
1&
#1460
b1001001 -
0&
b11100 .
#1470
1&
#1480
b10 ;
b10 P
b0 J
b0 I
b0 H
b1001010 -
0&
b11011 .
1'
#1490
b11 P
b11 ;
b10 Q
b10 <
1&
#1500
b1 ;
b1 P
b1 J
b1 I
b1 H
b1001011 -
0&
b11010 .
0'
#1510
b1 <
b1 Q
1&
#1520
b10 ;
b10 P
b0 J
b0 I
b0 H
b1001100 -
0&
b11001 .
1'
#1530
b11 P
b11 ;
b10 Q
b10 <
1&
#1540
b1 ;
b1 P
b1 J
b1 I
b1 H
b1001101 -
0&
b11000 .
0'
#1550
b1 <
b1 Q
1&
#1560
b10 ;
b10 P
b0 J
b0 I
b0 H
b1001110 -
0&
b10111 .
1'
#1570
b11 P
b11 ;
b10 Q
b10 <
1&
#1580
b1 ;
b1 P
b1 J
b1 I
b1 H
b1001111 -
0&
b10110 .
0'
#1590
b1 <
b1 Q
1&
#1600
b1010000 -
0&
b10101 .
#1610
1&
#1620
b10 ;
b10 P
b0 J
b0 I
b0 H
b1010001 -
0&
b10100 .
1'
#1630
b11 ;
b11 P
b10 <
b10 Q
1&
#1640
b1 ;
b1 P
b1 J
b1 I
b1 H
b1010010 -
0&
b10011 .
0'
#1650
b1 Q
b1 <
1&
#1660
b10 ;
b10 P
b0 J
b0 I
b0 H
b1010011 -
0&
b10010 .
1'
#1670
b11 ;
b11 P
b10 <
b10 Q
1&
#1680
b1 ;
b1 P
b1 J
b1 I
b1 H
b1010100 -
0&
b10001 .
0'
#1690
b1 Q
b1 <
1&
#1700
b10 ;
b10 P
b0 J
b0 I
b0 H
b1010101 -
0&
b10000 .
1'
#1710
b11 ;
b11 P
b10 <
b10 Q
1&
#1720
b1010110 -
0&
b1111 .
#1730
b0 P
b0 ;
b11 Q
b11 <
1&
#1740
b1 ;
b1 J
b1 I
b1 H
b1010111 -
0&
b1110 .
0'
#1750
b1 P
1"
b1 <
1!
b0 Q
1&
#1760
b10 ;
b0 P
b0 J
b0 I
b0 H
b100000000000000 *
1%
b1011000 -
0&
b1101 .
1'
#1770
b11 ;
0!
0"
b10 <
1&
#1780
0%
b1011001 -
0&
b1100 .
#1790
b0 ;
b11 <
1&
#1800
b1 ;
b1 P
b1 J
b1 I
b1 H
b1011010 -
0&
b1011 .
0'
#1810
b1 Q
1"
b1 <
1&
#1820
b10 ;
b10 P
b0 J
b0 I
b0 H
b100100000000000 *
1%
b1011011 -
0&
b1010 .
1'
#1830
b11 ;
b11 P
0"
b10 <
b10 Q
1&
#1840
0%
b1011100 -
0&
b1001 .
#1850
b0 P
b0 ;
b11 Q
b11 <
1&
#1860
b1 ;
b1 J
b1 I
b1 H
b1011101 -
0&
b1000 .
0'
#1870
b1 P
1"
b1 <
1!
b0 Q
1&
#1880
b10 ;
b0 P
b0 J
b0 I
b0 H
b100100100000000 *
1%
b1011110 -
0&
b111 .
1'
#1890
b11 ;
0!
0"
b10 <
1&
#1900
0%
b1011111 -
0&
b110 .
#1910
b0 ;
b11 <
1&
#1920
b1 ;
b1 P
b1 J
b1 I
b1 H
b1100000 -
0&
b101 .
0'
#1930
b1 Q
1"
b1 <
1&
#1940
b10 ;
b10 P
b0 J
b0 I
b0 H
b100100100100000 *
1%
b1100001 -
0&
b100 .
1'
#1950
b11 ;
b11 P
0"
b10 <
b10 Q
1&
#1960
0%
b1100010 -
0&
b11 .
#1970
b0 P
b0 ;
b11 Q
b11 <
1&
#1980
b1 ;
b1 J
b1 I
b1 H
b1100011 -
0&
b10 .
0'
#1990
b1 P
1"
b1 <
1!
b0 Q
1&
#2000
b10 ;
b0 P
b0 J
b0 I
b0 H
b100100100100100 *
1%
b1100100 -
0&
b1 .
1'
#2010
b11 ;
0!
0"
b10 <
1&
#2020
b1 ;
b1 P
b1 J
b1 I
b1 H
0%
b1100101 -
0&
b0 .
0'
#2030
b1 <
b1 Q
1&
#2040
b0 Q
b0 <
b1100110 -
0&
0)
b1 /
#2050
1&
#2060
b1100111 -
0&
b100000 .
b100000100000100 ,
b100 0
b0 *
1)
#2070
b1 Q
b1 <
1&
#2080
b1101000 -
0&
b11111 .
#2090
1&
#2100
b10 ;
b10 P
b0 J
b0 I
b0 H
b1101001 -
0&
b11110 .
1'
#2110
b11 P
b11 ;
b10 Q
b10 <
1&
#2120
b1 ;
b1 P
b1 J
b1 I
b1 H
b1101010 -
0&
b11101 .
0'
#2130
b1 <
b1 Q
1&
#2140
b1101011 -
0&
b11100 .
#2150
1&
#2160
b10 ;
b10 P
b0 J
b0 I
b0 H
b1101100 -
0&
b11011 .
1'
#2170
b11 ;
b11 P
b10 <
b10 Q
1&
#2180
b1 ;
b1 P
b1 J
b1 I
b1 H
b1101101 -
0&
b11010 .
0'
#2190
b1 Q
b1 <
1&
#2200
b10 ;
b10 P
b0 J
b0 I
b0 H
b1101110 -
0&
b11001 .
1'
#2210
b11 ;
b11 P
b10 <
b10 Q
1&
#2220
b1 ;
b1 P
b1 J
b1 I
b1 H
b1101111 -
0&
b11000 .
0'
#2230
b1 Q
b1 <
1&
#2240
b10 ;
b10 P
b0 J
b0 I
b0 H
b1110000 -
0&
b10111 .
1'
#2250
b11 ;
b11 P
b10 <
b10 Q
1&
#2260
b1 ;
b1 P
b1 J
b1 I
b1 H
b1110001 -
0&
b10110 .
0'
#2270
b1 Q
b1 <
1&
#2280
b1110010 -
0&
b10101 .
#2290
1&
#2300
b10 ;
b10 P
b0 J
b0 I
b0 H
b1110011 -
0&
b10100 .
1'
#2310
b11 P
b11 ;
b10 Q
b10 <
1&
#2320
b1 ;
b1 P
b1 J
b1 I
b1 H
b1110100 -
0&
b10011 .
0'
#2330
b1 <
b1 Q
1&
#2340
b10 ;
b10 P
b0 J
b0 I
b0 H
b1110101 -
0&
b10010 .
1'
#2350
b11 P
b11 ;
b10 Q
b10 <
1&
#2360
b1 ;
b1 P
b1 J
b1 I
b1 H
b1110110 -
0&
b10001 .
0'
#2370
b1 <
b1 Q
1&
#2380
b10 ;
b10 P
b0 J
b0 I
b0 H
b1110111 -
0&
b10000 .
1'
#2390
b11 P
b11 ;
b10 Q
b10 <
1&
#2400
b1111000 -
0&
b1111 .
#2410
b0 ;
b0 P
b11 <
b11 Q
1&
#2420
b1 ;
b1 J
b1 I
b1 H
b1111001 -
0&
b1110 .
0'
#2430
b1 P
1!
b0 Q
1"
b1 <
1&
#2440
b10 ;
b0 P
b0 J
b0 I
b0 H
b100000000000000 *
1%
b1111010 -
0&
b1101 .
1'
#2450
b11 ;
0"
b10 <
0!
1&
#2460
0%
b1111011 -
0&
b1100 .
#2470
b0 ;
b11 <
1&
#2480
b1 ;
b1 P
b1 J
b1 I
b1 H
b1111100 -
0&
b1011 .
0'
#2490
1"
b1 <
b1 Q
1&
#2500
b10 ;
b10 P
b0 J
b0 I
b0 H
b1111101 -
0&
b1010 .
1'
#2510
b11 P
b11 ;
b10 Q
0"
b10 <
1&
#2520
b1111110 -
0&
b1001 .
#2530
b0 ;
b0 P
b11 <
b11 Q
1&
#2540
b1 ;
b1 J
b1 I
b1 H
b1111111 -
0&
b1000 .
0'
#2550
b1 P
1!
b0 Q
1"
b1 <
1&
#2560
b10 ;
b0 P
b0 J
b0 I
b0 H
b100000100000000 *
1%
b10000000 -
0&
b111 .
1'
#2570
b11 ;
0"
b10 <
0!
1&
#2580
0%
b10000001 -
0&
b110 .
#2590
b0 ;
b11 <
1&
#2600
b1 ;
b1 P
b1 J
b1 I
b1 H
b10000010 -
0&
b101 .
0'
#2610
1"
b1 <
b1 Q
1&
#2620
b10 ;
b10 P
b0 J
b0 I
b0 H
b10000011 -
0&
b100 .
1'
#2630
b11 P
b11 ;
b10 Q
0"
b10 <
1&
#2640
b10000100 -
0&
b11 .
#2650
b0 ;
b0 P
b11 <
b11 Q
1&
#2660
b1 ;
b1 J
b1 I
b1 H
b10000101 -
0&
b10 .
0'
#2670
b1 P
1!
b0 Q
1"
b1 <
1&
#2680
b10 ;
b0 P
b0 J
b0 I
b0 H
b100000100000100 *
1%
b10000110 -
0&
b1 .
1'
#2690
b11 ;
0"
b10 <
0!
1&
#2700
b1 ;
b1 P
b1 J
b1 I
b1 H
0%
b10000111 -
0&
b0 .
0'
#2710
b1 Q
b1 <
1&
#2720
b0 <
b0 Q
b10001000 -
0&
0)
