UART/clock_divider.sv
/*
    Clock divider (Baud Rate Generation)

If divider value is unknown then clk out is a constant 1

f="clock_divider.sv"; m="clock_divider";
yosys -p "read_verilog -sv ${f}; hierarchy -check -top $m; proc; opt; clean; show -format svg -prefix ${m} ${m}; show ${m}"
*/
module clock_divider #(parameter DIV_WIDTH = 16) (
    input res_n,
    input clk_in,
    input [DIV_WIDTH-1:0] div,
    output logic clk_out
);
    logic [DIV_WIDTH-1:0] counter, next_count;
    logic cycle_init, cycle_full, switch_clk, half_cycle;

    assign cycle_init   = counter == 1;
    assign cycle_full   = counter == div;
    assign half_cycle   = counter == {1'b0, div[DIV_WIDTH-1:1]};// counter == div >> 1
    assign switch_clk   = cycle_full | half_cycle;              // odd dividers will not get exact 50% phase
    assign next_count   = counter + 1;

    always_ff @(posedge clk_in or negedge res_n) begin
        if (~res_n)
            counter <= 1;
        else if (cycle_full)
            counter <= 1;
        else
            counter <= next_count;
    end
    always_ff @(posedge clk_in or negedge res_n) begin
        if (~res_n)
            clk_out <= 1'b1;
        else if (switch_clk)
            clk_out <= ~clk_out;
        else if ($isunknown(switch_clk))
            clk_out <= 1'b1;
    end
endmodule

UART/testbench.sv
`define TCLK 5  // 100Mhz
`timescale 1ns / 1ns

/*
src="testbench.sv clock_divider.sv"
iverilog -Wall -g2012 -I ../ -o dir/baud_tb.vvp -s baud_tb ${src};
vvp dir/baud_tb.vvp
*/
module baud_tb;
    logic clk;
    logic res_n = 1'b0;
    logic clk_out2, clk_out3, clk_out4, clk_out5, clk_out6, clk_out7, clk_out8, clk_out9, clk_out10;

    clock_divider uut2 (.clk_in(clk), .res_n(res_n), .div(16'd2), .clk_out(clk_out2));
    clock_divider uut3 (.clk_in(clk), .res_n(res_n), .div(16'd3), .clk_out(clk_out3));
    clock_divider uut4 (.clk_in(clk), .res_n(res_n), .div(16'd4), .clk_out(clk_out4));
    clock_divider uut5 (.clk_in(clk), .res_n(res_n), .div(16'd5), .clk_out(clk_out5));
    clock_divider uut6 (.clk_in(clk), .res_n(res_n), .div(16'd6), .clk_out(clk_out6));
    clock_divider uut7 (.clk_in(clk), .res_n(res_n), .div(16'd7), .clk_out(clk_out7));
    clock_divider uut8 (.clk_in(clk), .res_n(res_n), .div(16'd8), .clk_out(clk_out8));
    clock_divider uut9 (.clk_in(clk), .res_n(res_n), .div(16'd9), .clk_out(clk_out9));
    clock_divider uut10 (.clk_in(clk), .res_n(res_n), .div(16'd10), .clk_out(clk_out10));

    always #`TCLK clk = ~clk;
    initial begin
        $dumpfile("dir/baud_tb.vcd");
        $dumpvars(0, baud_tb);
        clk = 1'b1;
        res_n = 1'b1;
        @(posedge clk) res_n = 1'b0;
        @(posedge clk);
        @(posedge clk) res_n = 1'b1;
        #5000 $finish;
    end
endmodule


/*
src="testbench.sv uart_rx.sv clock_divider.sv ../shift_reg.v"
iverilog -Wall -g2012 -I ../ -o dir/uart_rx_tb.vvp -s uart_rx_tb ${src};
vvp dir/uart_rx_tb.vvp
*/
module uart_rx_tb;
    localparam DATA_WIDTH = 8;
    logic clk;
    logic res_n;
    logic valid;
    logic din;
    logic b_tick;
    logic err_par;
    logic err_fr;
    logic [DATA_WIDTH-1:0] uart_rx_out;
    localparam DIV = 16'h4;
    localparam baud_wait = `TCLK*2*16*DIV;

    clock_divider rx_baud (.clk_in(clk), .res_n(res_n), .div(DIV), .clk_out(b_tick));

    uart_rx #(DATA_WIDTH) dut (
        .clk(clk),
        .res_n(res_n),
        .rx_baud(b_tick),
        .rx_din(din),
        .rx_out(uart_rx_out),
        .rx_ready(valid),
        .err_par(err_par),
        .err_fr(err_fr)
    );

    always #`TCLK clk  = ~clk;

    task driver(input logic [DATA_WIDTH-1:0] tx_data);
        int i;
        begin
            // start bit
            #baud_wait din = 1'b0;
            // data bits
            for (i = 0; i < DATA_WIDTH; i = i + 1)    
                #baud_wait din = tx_data[i];
            // parity
            #baud_wait din = ^tx_data;
            // stop bits
            #baud_wait din = 1'b1;
            #baud_wait din = 1'b1;
            // some wait
            #baud_wait;
            #baud_wait;
        end
    endtask

    initial begin
        $dumpfile("dir/uart_rx_tb.vcd");
        $dumpvars(0);
        $monitor("%t RX: din=%0b dout=%0b, rx_ready=%0b, err_par=%0b, err_fr=%0b", $time, din, uart_rx_out, valid, err_par, err_fr);
        clk = 1'b1;
        res_n = 1'b1;
        @(posedge clk) res_n = 1'b0;
        repeat(2) @(posedge clk);
        res_n = 1'b1;
        din = 1'b1;
        driver(8'hB2);
        driver(8'hAA);
        driver(8'h95);
        $finish;
    end
endmodule


/*
src="testbench.sv uart_tx.sv clock_divider.sv ../shift_reg.v"
iverilog -Wall -g2012 -I ../ -o dir/uart_tx_tb.vvp -s uart_tx_tb ${src};
vvp dir/uart_tx_tb.vvp
*/
module uart_tx_tb;
    logic clk;
    logic res_n;
    logic en;
    logic uart_tx_out;
    logic valid;
    logic b_tick;
    logic [7:0] din;
    localparam DIV = 4;

    clock_divider tx_baud (.clk_in(clk), .res_n(res_n), .div(DIV), .clk_out(b_tick));

    uart_tx #(8) dut (
        .clk(clk),
        .res_n(res_n),
        .tx_baud(b_tick),
        .tx_start(en),
        .tx_din(din),
        .tx_dout(uart_tx_out),
        .tx_ready(valid)
    );

    always #`TCLK clk  = ~clk;
    initial begin
        $dumpfile("dir/uart_tx_tb.vcd");
        $dumpvars(0);
        $monitor("%t TX: din=%0b dout=%0b", $time, din, uart_tx_out);
        clk = 1'b1;
        res_n = 1'b1;
        @(posedge clk) res_n = 1'b0;
        repeat(2) @(posedge clk);
        res_n = 1'b1;
        //@(posedge clk) res_n = 1'b0;
        repeat(16*DIV) @(posedge clk);
        din = 8'hB2;
        en = 1'b1;
        repeat(2) @(posedge clk);
        @(posedge valid);
        din = 8'hAA;
        @(posedge valid);
        repeat(48*DIV) @(posedge clk);
        $finish;
    end
endmodule


/*
src="testbench.sv uart.sv clock_divider.sv uart_tx.sv uart_rx.sv ../fifo.v ../shift_reg.v"
iverilog -Wall -g2012 -I ../ -o dir/uart_tb.vvp -s uart_tb ${src};
vvp dir/uart_tb.vvp
*/
module uart_tb;
    localparam DATA_WIDTH = 8;
    logic clk;
    logic res_n;
    logic [11:0] divisor;
    logic rd_uart;
    logic wr_uart;
    logic tx_ext;
    logic rx_empty;
    logic tx_full;
    logic [DATA_WIDTH-1:0] rd_data, wr_data;
    int byte_wait;

    uart uut (
        .clk(clk),
        .res_n(res_n),
        .divisor(divisor),
        .wr_data(wr_data),
        .rd_uart(rd_uart),
        .wr_uart(wr_uart),
        .rx_ext(tx_ext),
        .tx_ext(tx_ext),
        .rx_empty(rx_empty),
        .tx_full(tx_full),
        .rd_data(rd_data)
    );
    
    always #5 clk = ~clk;
    assign rd_uart = ~rx_empty;

    initial begin
        $dumpfile("dir/UART_VTB.vcd");
        $dumpvars();
        $monitor("%t [TB INFO] wr_data=%0h rd_data=%0h", $time, wr_data, rd_data);
        clk = 0;
        res_n = 1;
        divisor = 430; // 100mhz / 16*(9600*12/8)
        byte_wait = divisor * 16 * 12;
        @(posedge clk) res_n = 0;
        @(posedge clk) res_n = 1;

        @(negedge clk) wr_uart = 1;
        wr_data = 'hAB;
        @(negedge clk) wr_uart = 0;
        wait(rd_data == 'hAB);
        repeat(byte_wait) @(negedge clk); // some pause before proceeding

        @(negedge clk) wr_uart = 1;
        wr_data = 'hDA;
        @(negedge clk) wr_data = 'hC2;
        @(negedge clk) wr_data = 'hB9;
        @(negedge clk) wr_data = 'hB2;
        @(negedge clk) wr_uart = 0;
        repeat(byte_wait*5) @(posedge clk);

        $display("UART TB FINISH");
        $finish;
    end
endmodule

UART/dir/baud_tb.vcd
$date
	Fri Mar 13 09:32:07 2026
$end
$version
	Icarus Verilog
$end
$timescale
	1ns
$end
$scope module baud_tb $end
$var wire 1 ! clk_out9 $end
$var wire 1 " clk_out8 $end
$var wire 1 # clk_out7 $end
$var wire 1 $ clk_out6 $end
$var wire 1 % clk_out5 $end
$var wire 1 & clk_out4 $end
$var wire 1 ' clk_out3 $end
$var wire 1 ( clk_out2 $end
$var wire 1 ) clk_out10 $end
$var reg 1 * clk $end
$var reg 1 + res_n $end
$scope module uut10 $end
$var wire 1 * clk_in $end
$var wire 12 , div [11:0] $end
$var wire 1 + res_n $end
$var wire 1 - switch_clk $end
$var wire 12 . next_count [11:0] $end
$var wire 1 / half_cycle $end
$var wire 1 0 cycle_init $end
$var wire 1 1 cycle_full $end
$var parameter 32 2 DIV_WIDTH $end
$var reg 1 ) clk_out $end
$var reg 12 3 counter [11:0] $end
$upscope $end
$scope module uut2 $end
$var wire 1 * clk_in $end
$var wire 12 4 div [11:0] $end
$var wire 1 + res_n $end
$var wire 1 5 switch_clk $end
$var wire 12 6 next_count [11:0] $end
$var wire 1 7 half_cycle $end
$var wire 1 8 cycle_init $end
$var wire 1 9 cycle_full $end
$var parameter 32 : DIV_WIDTH $end
$var reg 1 ( clk_out $end
$var reg 12 ; counter [11:0] $end
$upscope $end
$scope module uut3 $end
$var wire 1 * clk_in $end
$var wire 12 < div [11:0] $end
$var wire 1 + res_n $end
$var wire 1 = switch_clk $end
$var wire 12 > next_count [11:0] $end
$var wire 1 ? half_cycle $end
$var wire 1 @ cycle_init $end
$var wire 1 A cycle_full $end
$var parameter 32 B DIV_WIDTH $end
$var reg 1 ' clk_out $end
$var reg 12 C counter [11:0] $end
$upscope $end
$scope module uut4 $end
$var wire 1 * clk_in $end
$var wire 12 D div [11:0] $end
$var wire 1 + res_n $end
$var wire 1 E switch_clk $end
$var wire 12 F next_count [11:0] $end
$var wire 1 G half_cycle $end
$var wire 1 H cycle_init $end
$var wire 1 I cycle_full $end
$var parameter 32 J DIV_WIDTH $end
$var reg 1 & clk_out $end
$var reg 12 K counter [11:0] $end
$upscope $end
$scope module uut5 $end
$var wire 1 * clk_in $end
$var wire 12 L div [11:0] $end
$var wire 1 + res_n $end
$var wire 1 M switch_clk $end
$var wire 12 N next_count [11:0] $end
$var wire 1 O half_cycle $end
$var wire 1 P cycle_init $end
$var wire 1 Q cycle_full $end
$var parameter 32 R DIV_WIDTH $end
$var reg 1 % clk_out $end
$var reg 12 S counter [11:0] $end
$upscope $end
$scope module uut6 $end
$var wire 1 * clk_in $end
$var wire 12 T div [11:0] $end
$var wire 1 + res_n $end
$var wire 1 U switch_clk $end
$var wire 12 V next_count [11:0] $end
$var wire 1 W half_cycle $end
$var wire 1 X cycle_init $end
$var wire 1 Y cycle_full $end
$var parameter 32 Z DIV_WIDTH $end
$var reg 1 $ clk_out $end
$var reg 12 [ counter [11:0] $end
$upscope $end
$scope module uut7 $end
$var wire 1 * clk_in $end
$var wire 12 \ div [11:0] $end
$var wire 1 + res_n $end
$var wire 1 ] switch_clk $end
$var wire 12 ^ next_count [11:0] $end
$var wire 1 _ half_cycle $end
$var wire 1 ` cycle_init $end
$var wire 1 a cycle_full $end
$var parameter 32 b DIV_WIDTH $end
$var reg 1 # clk_out $end
$var reg 12 c counter [11:0] $end
$upscope $end
$scope module uut8 $end
$var wire 1 * clk_in $end
$var wire 12 d div [11:0] $end
$var wire 1 + res_n $end
$var wire 1 e switch_clk $end
$var wire 12 f next_count [11:0] $end
$var wire 1 g half_cycle $end
$var wire 1 h cycle_init $end
$var wire 1 i cycle_full $end
$var parameter 32 j DIV_WIDTH $end
$var reg 1 " clk_out $end
$var reg 12 k counter [11:0] $end
$upscope $end
$scope module uut9 $end
$var wire 1 * clk_in $end
$var wire 12 l div [11:0] $end
$var wire 1 + res_n $end
$var wire 1 m switch_clk $end
$var wire 12 n next_count [11:0] $end
$var wire 1 o half_cycle $end
$var wire 1 p cycle_init $end
$var wire 1 q cycle_full $end
$var parameter 32 r DIV_WIDTH $end
$var reg 1 ! clk_out $end
$var reg 12 s counter [11:0] $end
$upscope $end
$upscope $end
$enddefinitions $end
$comment Show the parameter values. $end
$dumpall
b1100 r
b1100 j
b1100 b
b1100 Z
b1100 R
b1100 J
b1100 B
b1100 :
b1100 2
$end
#0
$dumpvars
bx s
xq
xp
xo
bx n
xm
b1001 l
bx k
xi
xh
xg
bx f
xe
b1000 d
bx c
xa
x`
x_
bx ^
x]
b111 \
bx [
xY
xX
xW
bx V
xU
b110 T
bx S
xQ
xP
xO
bx N
xM
b101 L
bx K
xI
xH
xG
bx F
xE
b100 D
bx C
xA
x@
x?
bx >
x=
b11 <
bx ;
x9
x8
x7
bx 6
x5
b10 4
bx 3
x1
x0
x/
bx .
x-
b1010 ,
1+
1*
x)
x(
x'
x&
x%
x$
x#
x"
x!
$end
#5
0*
#10
10
0-
1p
0m
1h
0e
1`
0]
1X
0U
1P
0M
1H
0E
1@
1=
18
15
0)
01
0/
b10 .
b1 3
0!
0q
0o
b10 n
b1 s
0"
0i
0g
b10 f
b1 k
0#
0a
0_
b10 ^
b1 c
0$
0Y
0W
b10 V
b1 [
0%
0Q
0O
b10 N
b1 S
0&
0I
0G
b10 F
b1 K
0'
0A
1?
b10 >
b1 C
0(
09
17
b10 6
b1 ;
0+
1*
#15
0*
#20
1*
#25
0*
#30
00
0p
0h
0`
0X
0P
1M
0H
1E
0@
0=
08
b11 .
b10 3
b11 n
b10 s
b11 f
b10 k
b11 ^
b10 c
b11 V
b10 [
1O
b11 N
b10 S
1G
b11 F
b10 K
1'
0?
b11 >
b10 C
1(
19
07
b11 6
b10 ;
1+
1*
#35
0*
#40
18
1=
0E
0M
1U
1]
09
17
b10 6
b1 ;
0(
1A
b100 >
b11 C
0G
b100 F
b11 K
1&
0O
b100 N
b11 S
1%
1W
b100 V
b11 [
1_
b100 ^
b11 c
b100 f
b11 k
b100 n
b11 s
b100 .
b11 3
1*
#45
0*
#50
1m
1e
0]
0U
1E
1@
08
b101 .
b100 3
1o
b101 n
b100 s
1g
b101 f
b100 k
1#
0_
b101 ^
b100 c
1$
0W
b101 V
b100 [
b101 N
b100 S
1I
b101 F
b100 K
0'
0A
1?
b10 >
b1 C
1(
19
07
b11 6
b10 ;
1*
#55
0*
#60
18
0@
0=
1H
0E
1M
0e
0m
1-
09
17
b10 6
b1 ;
0(
0?
b11 >
b10 C
1'
0I
b10 F
b1 K
0&
1Q
b110 N
b101 S
b110 V
b101 [
b110 ^
b101 c
0g
b110 f
b101 k
1"
0o
b110 n
b101 s
1!
1/
b110 .
b101 3
1*
#65
0*
#70
0-
1U
1P
0M
0H
1E
1=
08
1)
0/
b111 .
b110 3
b111 n
b110 s
b111 f
b110 k
b111 ^
b110 c
1Y
b111 V
b110 [
0%
0Q
b10 N
b1 S
1G
b11 F
b10 K
1A
b100 >
b11 C
1(
19
07
b11 6
b10 ;
1*
#75
0*
#80
18
1@
0E
0P
1M
1X
0U
1]
09
17
b10 6
b1 ;
0(
0A
1?
b10 >
b1 C
0'
0G
b100 F
b11 K
1&
1O
b11 N
b10 S
0Y
b10 V
b1 [
0$
1a
b1000 ^
b111 c
b1000 f
b111 k
b1000 n
b111 s
b1000 .
b111 3
1*
#85
0*
#90
1e
1`
0]
0X
0M
1E
0@
0=
08
b1001 .
b1000 3
b1001 n
b1000 s
1i
b1001 f
b1000 k
0#
0a
b10 ^
b1 c
b11 V
b10 [
1%
0O
b100 N
b11 S
1I
b101 F
b100 K
1'
0?
b11 >
b10 C
1(
19
07
b11 6
b10 ;
1*
#95
0*
#100
18
1=
1H
0E
1U
0`
1h
0e
1m
09
17
b10 6
b1 ;
0(
1A
b100 >
b11 C
0I
b10 F
b1 K
0&
b101 N
b100 S
1W
b100 V
b11 [
b11 ^
b10 c
0i
b10 f
b1 k
0"
1q
b1010 n
b1001 s
b1010 .
b1001 3
1*
#105
0*
#110
1-
1p
0m
0h
1]
0U
1M
0H
1E
1@
08
11
b1011 .
b1010 3
0!
0q
b10 n
b1 s
b11 f
b10 k
1_
b100 ^
b11 c
1$
0W
b101 V
b100 [
1Q
b110 N
b101 S
1G
b11 F
b10 K
0'
0A
1?
b10 >
b1 C
1(
19
07
b11 6
b10 ;
1*
#115
0*
#120
18
0@
0=
0E
1P
0M
0]
0p
10
0-
09
17
b10 6
b1 ;
0(
0?
b11 >
b10 C
1'
0G
b100 F
b11 K
1&
0Q
b10 N
b1 S
0%
b110 V
b101 [
0_
b101 ^
b100 c
1#
b100 f
b11 k
b11 n
b10 s
01
b10 .
b1 3
0)
1*
#125
0*
#130
00
1e
1U
0P
1M
1E
1=
08
b11 .
b10 3
b100 n
b11 s
1g
b101 f
b100 k
b110 ^
b101 c
1Y
b111 V
b110 [
1O
b11 N
b10 S
1I
b101 F
b100 K
1A
b100 >
b11 C
1(
19
07
b11 6
b10 ;
1*
#135
0*
#140
18
1@
1H
0E
0M
1X
0U
0e
1m
09
17
b10 6
b1 ;
0(
0A
1?
b10 >
b1 C
0'
0I
b10 F
b1 K
0&
0O
b100 N
b11 S
1%
0Y
b10 V
b1 [
0$
b111 ^
b110 c
0g
b110 f
b101 k
1"
1o
b101 n
b100 s
b100 .
b11 3
1*
#145
0*
#150
0m
1]
0X
0H
1E
0@
0=
08
b101 .
b100 3
1!
0o
b110 n
b101 s
b111 f
b110 k
1a
b1000 ^
b111 c
b11 V
b10 [
b101 N
b100 S
1G
b11 F
b10 K
1'
0?
b11 >
b10 C
1(
19
07
b11 6
b10 ;
1*
#155
0*
#160
18
1=
0E
1M
1U
1`
0]
1-
09
17
b10 6
b1 ;
0(
1A
b100 >
b11 C
0G
b100 F
b11 K
1&
1Q
b110 N
b101 S
1W
b100 V
b11 [
0a
b10 ^
b1 c
0#
b1000 f
b111 k
b111 n
b110 s
1/
b110 .
b101 3
1*
#165
0*
#170
0-
1e
0`
0U
1P
0M
1E
1@
08
1)
0/
b111 .
b110 3
b1000 n
b111 s
1i
b1001 f
b1000 k
b11 ^
b10 c
1$
0W
b101 V
b100 [
0%
0Q
b10 N
b1 S
1I
b101 F
b100 K
0'
0A
1?
b10 >
b1 C
1(
19
07
b11 6
b10 ;
1*
#175
0*
#180
18
0@
0=
1H
0E
0P
1M
1]
1h
0e
09
17
b10 6
b1 ;
0(
0?
b11 >
b10 C
1'
0I
b10 F
b1 K
0&
1O
b11 N
b10 S
b110 V
b101 [
1_
b100 ^
b11 c
0i
b10 f
b1 k
0"
b1001 n
b1000 s
b1000 .
b111 3
1*
#185
0*
#190
1m
0h
0]
1U
0M
0H
1E
1=
08
b1001 .
b1000 3
1q
b1010 n
b1001 s
b11 f
b10 k
1#
0_
b101 ^
b100 c
1Y
b111 V
b110 [
1%
0O
b100 N
b11 S
1G
b11 F
b10 K
1A
b100 >
b11 C
1(
19
07
b11 6
b10 ;
1*
#195
0*
#200
18
1@
0E
1X
0U
1p
0m
09
17
b10 6
b1 ;
0(
0A
1?
b10 >
b1 C
0'
0G
b100 F
b11 K
1&
b101 N
b100 S
0Y
b10 V
b1 [
0$
b110 ^
b101 c
b100 f
b11 k
0q
b10 n
b1 s
0!
b1010 .
b1001 3
1*
#205
0*
#210
1-
0p
1e
0X
1M
1E
0@
0=
08
11
b1011 .
b1010 3
b11 n
b10 s
1g
b101 f
b100 k
b111 ^
b110 c
b11 V
b10 [
1Q
b110 N
b101 S
1I
b101 F
b100 K
1'
0?
b11 >
b10 C
1(
19
07
b11 6
b10 ;
1*
#215
0*
#220
18
1=
1H
0E
1P
0M
1U
1]
0e
10
0-
09
17
b10 6
b1 ;
0(
1A
b100 >
b11 C
0I
b10 F
b1 K
0&
0Q
b10 N
b1 S
0%
1W
b100 V
b11 [
1a
b1000 ^
b111 c
0g
b110 f
b101 k
1"
b100 n
b11 s
01
b10 .
b1 3
0)
1*
#225
0*
#230
00
1m
1`
0]
0U
0P
1M
0H
1E
1@
08
b11 .
b10 3
1o
b101 n
b100 s
b111 f
b110 k
0#
0a
b10 ^
b1 c
1$
0W
b101 V
b100 [
1O
b11 N
b10 S
1G
b11 F
b10 K
0'
0A
1?
b10 >
b1 C
1(
19
07
b11 6
b10 ;
1*
#235
0*
#240
18
0@
0=
0E
0M
0`
0m
09
17
b10 6
b1 ;
0(
0?
b11 >
b10 C
1'
0G
b100 F
b11 K
1&
0O
b100 N
b11 S
1%
b110 V
b101 [
b11 ^
b10 c
b1000 f
b111 k
0o
b110 n
b101 s
1!
b100 .
b11 3
1*
#245
0*
#250
1e
1]
1U
1E
1=
08
b101 .
b100 3
b111 n
b110 s
1i
b1001 f
b1000 k
1_
b100 ^
b11 c
1Y
b111 V
b110 [
b101 N
b100 S
1I
b101 F
b100 K
1A
b100 >
b11 C
1(
19
07
b11 6
b10 ;
1*
#255
0*
#260
18
1@
1H
0E
1M
1X
0U
0]
1h
0e
1-
09
17
b10 6
b1 ;
0(
0A
1?
b10 >
b1 C
0'
0I
b10 F
b1 K
0&
1Q
b110 N
b101 S
0Y
b10 V
b1 [
0$
0_
b101 ^
b100 c
1#
0i
b10 f
b1 k
0"
b1000 n
b111 s
1/
b110 .
b101 3
1*
#265
0*
#270
0-
0h
0X
1P
0M
0H
1E
0@
0=
08
1)
0/
b111 .
b110 3
b1001 n
b1000 s
b11 f
b10 k
b110 ^
b101 c
b11 V
b10 [
0%
0Q
b10 N
b1 S
1G
b11 F
b10 K
1'
0?
b11 >
b10 C
1(
19
07
b11 6
b10 ;
1*
#275
0*
#280
18
1=
0E
0P
1M
1U
1m
09
17
b10 6
b1 ;
0(
1A
b100 >
b11 C
0G
b100 F
b11 K
1&
1O
b11 N
b10 S
1W
b100 V
b11 [
b111 ^
b110 c
b100 f
b11 k
1q
b1010 n
b1001 s
b1000 .
b111 3
1*
#285
0*
#290
1p
0m
1e
1]
0U
0M
1E
1@
08
b1001 .
b1000 3
0!
0q
b10 n
b1 s
1g
b101 f
b100 k
1a
b1000 ^
b111 c
1$
0W
b101 V
b100 [
1%
0O
b100 N
b11 S
1I
b101 F
b100 K
0'
0A
1?
b10 >
b1 C
1(
19
07
b11 6
b10 ;
1*
#295
0*
#300
18
0@
0=
1H
0E
1`
0]
0e
0p
09
17
b10 6
b1 ;
0(
0?
b11 >
b10 C
1'
0I
b10 F
b1 K
0&
b101 N
b100 S
b110 V
b101 [
0a
b10 ^
b1 c
0#
0g
b110 f
b101 k
1"
b11 n
b10 s
b1010 .
b1001 3
1*
#305
0*
#310
1-
0`
1U
1M
0H
1E
1=
08
11
b1011 .
b1010 3
b100 n
b11 s
b111 f
b110 k
b11 ^
b10 c
1Y
b111 V
b110 [
1Q
b110 N
b101 S
1G
b11 F
b10 K
1A
b100 >
b11 C
1(
19
07
b11 6
b10 ;
1*
#315
0*
#320
18
1@
0E
1P
0M
1X
0U
1]
1m
10
0-
09
17
b10 6
b1 ;
0(
0A
1?
b10 >
b1 C
0'
0G
b100 F
b11 K
1&
0Q
b10 N
b1 S
0%
0Y
b10 V
b1 [
0$
1_
b100 ^
b11 c
b1000 f
b111 k
1o
b101 n
b100 s
01
b10 .
b1 3
0)
1*
#325
0*
#330
00
0m
1e
0]
0X
0P
1M
1E
0@
0=
08
b11 .
b10 3
1!
0o
b110 n
b101 s
1i
b1001 f
b1000 k
1#
0_
b101 ^
b100 c
b11 V
b10 [
1O
b11 N
b10 S
1I
b101 F
b100 K
1'
0?
b11 >
b10 C
1(
19
07
b11 6
b10 ;
1*
#335
0*
#340
18
1=
1H
0E
0M
1U
1h
0e
09
17
b10 6
b1 ;
0(
1A
b100 >
b11 C
0I
b10 F
b1 K
0&
0O
b100 N
b11 S
1%
1W
b100 V
b11 [
b110 ^
b101 c
0i
b10 f
b1 k
0"
b111 n
b110 s
b100 .
b11 3
1*
#345
0*
#350
0h
0U
0H
1E
1@
08
b101 .
b100 3
b1000 n
b111 s
b11 f
b10 k
b111 ^
b110 c
1$
0W
b101 V
b100 [
b101 N
b100 S
1G
b11 F
b10 K
0'
0A
1?
b10 >
b1 C
1(
19
07
b11 6
b10 ;
1*
#355
0*
#360
18
0@
0=
0E
1M
1]
1-
09
17
b10 6
b1 ;
0(
0?
b11 >
b10 C
1'
0G
b100 F
b11 K
1&
1Q
b110 N
b101 S
b110 V
b101 [
1a
b1000 ^
b111 c
b100 f
b11 k
b1001 n
b1000 s
1/
b110 .
b101 3
1*
#365
0*
#370
0-
1m
1e
1`
0]
1U
1P
0M
1E
1=
08
1)
0/
b111 .
b110 3
1q
b1010 n
b1001 s
1g
b101 f
b100 k
0#
0a
b10 ^
b1 c
1Y
b111 V
b110 [
0%
0Q
b10 N
b1 S
1I
b101 F
b100 K
1A
b100 >
b11 C
1(
19
07
b11 6
b10 ;
1*
#375
0*
#380
18
1@
1H
0E
0P
1M
1X
0U
0`
0e
1p
0m
09
17
b10 6
b1 ;
0(
0A
1?
b10 >
b1 C
0'
0I
b10 F
b1 K
0&
1O
b11 N
b10 S
0Y
b10 V
b1 [
0$
b11 ^
b10 c
0g
b110 f
b101 k
1"
0q
b10 n
b1 s
0!
b1000 .
b111 3
1*
#385
0*
#390
0p
1]
0X
0M
0H
1E
0@
0=
08
b1001 .
b1000 3
b11 n
b10 s
b111 f
b110 k
1_
b100 ^
b11 c
b11 V
b10 [
1%
0O
b100 N
b11 S
1G
b11 F
b10 K
1'
0?
b11 >
b10 C
1(
19
07
b11 6
b10 ;
1*
#395
0*
#400
18
1=
0E
1U
0]
09
17
b10 6
b1 ;
0(
1A
b100 >
b11 C
0G
b100 F
b11 K
1&
b101 N
b100 S
1W
b100 V
b11 [
0_
b101 ^
b100 c
1#
b1000 f
b111 k
b100 n
b11 s
b1010 .
b1001 3
1*
#405
0*
#410
1-
1m
1e
0U
1M
1E
1@
08
11
b1011 .
b1010 3
1o
b101 n
b100 s
1i
b1001 f
b1000 k
b110 ^
b101 c
1$
0W
b101 V
b100 [
1Q
b110 N
b101 S
1I
b101 F
b100 K
0'
0A
1?
b10 >
b1 C
1(
19
07
b11 6
b10 ;
1*
#415
0*
#420
18
0@
0=
1H
0E
1P
0M
1h
0e
0m
10
0-
09
17
b10 6
b1 ;
0(
0?
b11 >
b10 C
1'
0I
b10 F
b1 K
0&
0Q
b10 N
b1 S
0%
b110 V
b101 [
b111 ^
b110 c
0i
b10 f
b1 k
0"
0o
b110 n
b101 s
1!
01
b10 .
b1 3
0)
1*
#425
0*
#430
00
0h
1]
1U
0P
1M
0H
1E
1=
08
b11 .
b10 3
b111 n
b110 s
b11 f
b10 k
1a
b1000 ^
b111 c
1Y
b111 V
b110 [
1O
b11 N
b10 S
1G
b11 F
b10 K
1A
b100 >
b11 C
1(
19
07
b11 6
b10 ;
1*
#435
0*
#440
18
1@
0E
0M
1X
0U
1`
0]
09
17
b10 6
b1 ;
0(
0A
1?
b10 >
b1 C
0'
0G
b100 F
b11 K
1&
0O
b100 N
b11 S
1%
0Y
b10 V
b1 [
0$
0a
b10 ^
b1 c
0#
b100 f
b11 k
b1000 n
b111 s
b100 .
b11 3
1*
#445
0*
#450
1e
0`
0X
1E
0@
0=
08
b101 .
b100 3
b1001 n
b1000 s
1g
b101 f
b100 k
b11 ^
b10 c
b11 V
b10 [
b101 N
b100 S
1I
b101 F
b100 K
1'
0?
b11 >
b10 C
1(
19
07
b11 6
b10 ;
1*
#455
0*
#460
18
1=
1H
0E
1M
1U
1]
0e
1m
1-
09
17
b10 6
b1 ;
0(
1A
b100 >
b11 C
0I
b10 F
b1 K
0&
1Q
b110 N
b101 S
1W
b100 V
b11 [
1_
b100 ^
b11 c
0g
b110 f
b101 k
1"
1q
b1010 n
b1001 s
1/
b110 .
b101 3
1*
#465
0*
#470
0-
1p
0m
0]
0U
1P
0M
0H
1E
1@
08
1)
0/
b111 .
b110 3
0!
0q
b10 n
b1 s
b111 f
b110 k
1#
0_
b101 ^
b100 c
1$
0W
b101 V
b100 [
0%
0Q
b10 N
b1 S
1G
b11 F
b10 K
0'
0A
1?
b10 >
b1 C
1(
19
07
b11 6
b10 ;
1*
#475
0*
#480
18
0@
0=
0E
0P
1M
0p
09
17
b10 6
b1 ;
0(
0?
b11 >
b10 C
1'
0G
b100 F
b11 K
1&
1O
b11 N
b10 S
b110 V
b101 [
b110 ^
b101 c
b1000 f
b111 k
b11 n
b10 s
b1000 .
b111 3
1*
#485
0*
#490
1e
1U
0M
1E
1=
08
b1001 .
b1000 3
b100 n
b11 s
1i
b1001 f
b1000 k
b111 ^
b110 c
1Y
b111 V
b110 [
1%
0O
b100 N
b11 S
1I
b101 F
b100 K
1A
b100 >
b11 C
1(
19
07
b11 6
b10 ;
1*
#495
0*
#500
18
1@
1H
0E
1X
0U
1]
1h
0e
1m
09
17
b10 6
b1 ;
0(
0A
1?
b10 >
b1 C
0'
0I
b10 F
b1 K
0&
b101 N
b100 S
0Y
b10 V
b1 [
0$
1a
b1000 ^
b111 c
0i
b10 f
b1 k
0"
1o
b101 n
b100 s
b1010 .
b1001 3
1*
#505
0*
#510
1-
0m
0h
1`
0]
0X
1M
0H
1E
0@
0=
08
11
b1011 .
b1010 3
1!
0o
b110 n
b101 s
b11 f
b10 k
0#
0a
b10 ^
b1 c
b11 V
b10 [
1Q
b110 N
b101 S
1G
b11 F
b10 K
1'
0?
b11 >
b10 C
1(
19
07
b11 6
b10 ;
1*
#515
0*
#520
18
1=
0E
1P
0M
1U
0`
10
0-
09
17
b10 6
b1 ;
0(
1A
b100 >
b11 C
0G
b100 F
b11 K
1&
0Q
b10 N
b1 S
0%
1W
b100 V
b11 [
b11 ^
b10 c
b100 f
b11 k
b111 n
b110 s
01
b10 .
b1 3
0)
1*
#525
0*
#530
00
1e
1]
0U
0P
1M
1E
1@
08
b11 .
b10 3
b1000 n
b111 s
1g
b101 f
b100 k
1_
b100 ^
b11 c
1$
0W
b101 V
b100 [
1O
b11 N
b10 S
1I
b101 F
b100 K
0'
0A
1?
b10 >
b1 C
1(
19
07
b11 6
b10 ;
1*
#535
0*
