adder_full_n.v
/*
    N bit FULL ADDER
*/
module adder_full_n(X, Y, Cin, sum, carry);
parameter n = 4;
input Cin;
input [n-1:0] X, Y;
output reg [n-1:0] sum;
output reg carry;
reg [n:0] C;
integer k;

always @(X, Y, Cin) begin
    C[0] = Cin;
    for (k = 0; k < n; k++) begin
        sum[k] = X[k] ^ Y[k] ^ C[k];
        C[k + 1] = (X[k] & Y[k]) | (X[k] & C[k]) | (Y[k] & C[k]);
    end
    carry = C[n];
end
endmodule


module full_adder_signed(X, Y, Cin, sum, carry, overflow);
    parameter n = 32;
    input Cin;
    input [n-1:0] X, Y;
    output reg [n-1:0] sum;
    output reg carry, overflow;
    
    always @(X, Y, Cin) begin
        {carry, sum} = X + Y + Cin;
        //sum = X ^ Y;
        //carry = (X & Y) | (X & Cin) | (Y & Cin);
        //overflow = (X[n-1] & Y[n-1] & ~S[n-1]) | (~X[n-1] & ~Y[n-1] & S[n-1]);
        overflow = X[n-1] & Y[n-1] & ~sum[n-1];
    end
endmodule

adder_full_n_tb.v
`timescale 1ns / 1ns;


module adder_full_n_tb();
    parameter n = 8;
    parameter DELAY = 5;
    reg Cin;
    reg [n-1:0] X, Y;
    wire [n-1:0] sum;
    wire carry;
    integer j, q, check_s, check_c;

    adder_full_n #(.n(n)) UUT(.X(X), .Y(Y), .Cin(Cin), .sum(sum), .carry(carry));

    initial begin
        $dumpfile("results/adder_full_n_tb.vcd");
        $dumpvars(0, adder_full_n_tb);
        $display("Test start");

        // Per stage test
        for (j = 0; j < n; j++) begin

            // test stuck at 1's
            X = 0; Y = 0; Cin = 0;
            #DELAY;
            if (sum[j] !== 0)
                $display("ERROR: sum %d is not equal to 0", sum);
            if (carry !== 0)
                $display("ERROR: carry %d is not equal to 0", carry);

            // test all paths per stage
            $display("Testing stage %d", j);
            for (q = 3'b001; q < 3'b111; q++) begin
                if (j == 0)
                    {Cin, X[j], Y[j]} = q;
                else
                    Y[j-1] = 1'b1;
                    {X[j-1], X[j], Y[j]} = q;
                if (q == 1 || q == 2 || q == 4) begin
                    check_s = 1;
                    check_c = 0;
                end else begin
                    check_s = 0;
                    check_c = 1;
                end
                #DELAY $display("%0d %0d: %8b: X=%b Y=%b %b: sum[%0d]=%d sum[j+1]=%d carry=%d (SUM=%d)", $time, j, q, X, Y, Cin, j, sum, sum[j+1], carry, sum);
                if (sum[j] !== check_s)
                    $display("%d %d: %b: ERROR: sum[%0d] %d is not equal to %d", $time, j, q, j, sum, check_s);
                if ((j < n-1 && sum[j+1] !== check_c) || (j == n-1 && carry !== check_c))
                    $display("%d %d: %b: ERROR: carry %d is not equal to %d", $time, j, q, sum[j+1], check_c);
            end
        end

        // test crosstalk
        X = 2**n - 1; Y = 2**n - 1; Cin = 1;
        #DELAY;
        if (sum !== 2**n - 1)
            $display("ERROR: sum %d is not equal to %d", sum, 2**n - 1);
        if (carry !== 1)
            $display("ERROR: carry %d is not equal to 1", carry);
        $display("%0d X=%b Y=%b %b: sum=%d carry=%d", $time, X, Y, Cin, sum, carry);
        $display("Test end");
        $finish;
    end
endmodule

results/adder_full_n_tb.vcd
$date
	Tue Dec 23 14:43:17 2025
$end
$version
	Icarus Verilog
$end
$timescale
	1ns
$end
$scope module adder_full_n_tb $end
$var wire 8 ! sum [7:0] $end
$var wire 1 " carry $end
$var parameter 32 # DELAY $end
$var parameter 32 $ n $end
$var reg 1 % Cin $end
$var reg 8 & X [7:0] $end
$var reg 8 ' Y [7:0] $end
$var integer 32 ( check_c [31:0] $end
$var integer 32 ) check_s [31:0] $end
$var integer 32 * j [31:0] $end
$var integer 32 + q [31:0] $end
$scope module UUT $end
$var wire 1 % Cin $end
$var wire 8 , X [7:0] $end
$var wire 8 - Y [7:0] $end
$var parameter 32 . n $end
$var reg 9 / C [8:0] $end
$var reg 1 " carry $end
$var reg 8 0 sum [7:0] $end
$var integer 32 1 k [31:0] $end
$upscope $end
$upscope $end
$enddefinitions $end
$comment Show the parameter values. $end
$dumpall
b1000 .
b1000 $
b101 #
$end
#0
$dumpvars
b1000 1
b0 0
b0 /
b0 -
b0 ,
bx +
b0 *
bx )
bx (
b0 '
b0 &
0%
0"
b0 !
$end
#5
b1 !
b1 0
b1000 1
b0 (
b1 )
b1 '
b1 -
b1 +
#10
b1000 1
b1 &
b1 ,
b0 '
b0 -
b10 +
#15
b10 /
b10 !
b10 0
b1000 1
b1 (
b0 )
b1 '
b1 -
b11 +
#20
b1 !
b1 0
b1000 1
b1 /
b0 (
b1 )
1%
b0 &
b0 ,
b0 '
b0 -
b100 +
#25
b11 /
b10 !
b10 0
b1000 1
b1 (
b0 )
b1 '
b1 -
b101 +
#30
b1000 1
b1 &
b1 ,
b0 '
b0 -
b110 +
#35
b0 !
b0 0
b1000 1
b0 /
0%
b0 &
b0 ,
b1 *
b111 +
#40
b11 !
b11 0
b1000 1
b0 (
b1 )
b11 '
b11 -
b1 +
#45
b1000 1
b10 &
b10 ,
b1 '
b1 -
b10 +
#50
b100 /
b101 !
b101 0
b1000 1
b1 (
b0 )
b11 '
b11 -
b11 +
#55
b10 /
b10 !
b10 0
b1000 1
b0 (
b1 )
b1 &
b1 ,
b1 '
b1 -
b100 +
#60
b110 /
b100 !
b100 0
b1000 1
b1 (
b0 )
b11 '
b11 -
b101 +
#65
b1000 1
b11 &
b11 ,
b1 '
b1 -
b110 +
#70
b0 !
b0 0
b0 /
b1000 1
b0 '
b0 -
b0 &
b0 ,
b10 *
b111 +
#75
b110 !
b110 0
b1000 1
b0 (
b1 )
b110 '
b110 -
b1 +
#80
b1000 1
b100 &
b100 ,
b10 '
b10 -
b10 +
#85
b1000 /
b1010 !
b1010 0
b1000 1
b1 (
b0 )
b110 '
b110 -
b11 +
#90
b100 /
b100 !
b100 0
b1000 1
b0 (
b1 )
b10 &
b10 ,
b10 '
b10 -
b100 +
#95
b1100 /
b1000 !
b1000 0
b1000 1
b1 (
b0 )
b110 '
b110 -
b101 +
#100
b1000 1
b110 &
b110 ,
b10 '
b10 -
b110 +
#105
b0 !
b0 0
b0 /
b1000 1
b0 '
b0 -
b0 &
b0 ,
b11 *
b111 +
#110
b1100 !
b1100 0
b1000 1
b0 (
b1 )
b1100 '
b1100 -
b1 +
#115
b1000 1
b1000 &
b1000 ,
b100 '
b100 -
b10 +
#120
b10000 /
b10100 !
b10100 0
b1000 1
b1 (
b0 )
b1100 '
b1100 -
b11 +
#125
b1000 /
b1000 !
b1000 0
b1000 1
b0 (
b1 )
b100 &
b100 ,
b100 '
b100 -
b100 +
#130
b11000 /
b10000 !
b10000 0
b1000 1
b1 (
b0 )
b1100 '
b1100 -
b101 +
#135
b1000 1
b1100 &
b1100 ,
b100 '
b100 -
b110 +
#140
b0 !
b0 0
b0 /
b1000 1
b0 '
b0 -
b0 &
b0 ,
b100 *
b111 +
#145
b11000 !
b11000 0
b1000 1
b0 (
b1 )
b11000 '
b11000 -
b1 +
#150
b1000 1
b10000 &
b10000 ,
b1000 '
b1000 -
b10 +
#155
b100000 /
b101000 !
b101000 0
b1000 1
b1 (
b0 )
b11000 '
b11000 -
b11 +
#160
b10000 /
b10000 !
b10000 0
b1000 1
b0 (
b1 )
b1000 &
b1000 ,
b1000 '
b1000 -
b100 +
#165
b110000 /
b100000 !
b100000 0
b1000 1
b1 (
b0 )
b11000 '
b11000 -
b101 +
#170
b1000 1
b11000 &
b11000 ,
b1000 '
b1000 -
b110 +
#175
b0 !
b0 0
b0 /
b1000 1
b0 '
b0 -
b0 &
b0 ,
b101 *
b111 +
#180
b110000 !
b110000 0
b1000 1
b0 (
b1 )
b110000 '
b110000 -
b1 +
#185
b1000 1
b100000 &
b100000 ,
b10000 '
b10000 -
b10 +
#190
b1000000 /
b1010000 !
b1010000 0
b1000 1
b1 (
b0 )
b110000 '
b110000 -
b11 +
#195
b100000 /
b100000 !
b100000 0
b1000 1
b0 (
b1 )
b10000 &
b10000 ,
b10000 '
b10000 -
b100 +
#200
b1100000 /
b1000000 !
b1000000 0
b1000 1
b1 (
b0 )
b110000 '
b110000 -
b101 +
#205
b1000 1
b110000 &
b110000 ,
b10000 '
b10000 -
b110 +
#210
b0 !
b0 0
b0 /
b1000 1
b0 '
b0 -
b0 &
b0 ,
b110 *
b111 +
#215
b1100000 !
b1100000 0
b1000 1
b0 (
b1 )
b1100000 '
b1100000 -
b1 +
#220
b1000 1
b1000000 &
b1000000 ,
b100000 '
b100000 -
b10 +
#225
b10000000 /
b10100000 !
b10100000 0
b1000 1
b1 (
b0 )
b1100000 '
b1100000 -
b11 +
#230
b1000000 /
b1000000 !
b1000000 0
b1000 1
b0 (
b1 )
b100000 &
b100000 ,
b100000 '
b100000 -
b100 +
#235
b11000000 /
b10000000 !
b10000000 0
b1000 1
b1 (
b0 )
b1100000 '
b1100000 -
b101 +
#240
b1000 1
b1100000 &
b1100000 ,
b100000 '
b100000 -
b110 +
#245
b0 !
b0 0
b0 /
b1000 1
b0 '
b0 -
b0 &
b0 ,
b111 *
b111 +
#250
b11000000 !
b11000000 0
b1000 1
b0 (
b1 )
b11000000 '
b11000000 -
b1 +
#255
b1000 1
b10000000 &
b10000000 ,
b1000000 '
b1000000 -
b10 +
#260
1"
b100000000 /
b1000000 !
b1000000 0
b1000 1
b1 (
b0 )
b11000000 '
b11000000 -
b11 +
#265
0"
b10000000 /
b10000000 !
b10000000 0
b1000 1
b0 (
b1 )
b1000000 &
b1000000 ,
b1000000 '
b1000000 -
b100 +
#270
1"
b110000000 /
b0 !
b0 0
b1000 1
b1 (
b0 )
b11000000 '
b11000000 -
b101 +
#275
b1000 1
b11000000 &
b11000000 ,
b1000000 '
b1000000 -
b110 +
#280
b11111111 !
b11111111 0
b1000 1
b111111111 /
1%
b11111111 '
b11111111 -
b11111111 &
b11111111 ,
b1000 *
b111 +
