adder_half.v
/*
f="adder_half"
m="adder_half_dataflow"
yosys -p "read_verilog ${f}.v; hierarchy -check -top $m; proc; flatten; opt; techmap; opt; share -aggressive; clean; stat; write_verilog -noattr synth/${f}_synth.v; show -format svg -prefix synth/${f}_${m} ${m}; show ${m}"
*/
module adder_half(output sum, output carry, input a, input b);
    and (carry, a, b);
    xor (sum, a, b);
endmodule


module adder_half_dataflow(output sum, output carry, input a, input b);
    specify
        // Specparam declaration to define timing parameters
        specparam TRiseA = 3; // Rise time delay
        specparam TRiseB = 2; // Fall time delay

        // Path declarations to specify delays between signals
        (a *> sum) = TRiseA;   // Delay from input 'a' to output 'out'/ Full connection
        (b => carry) = TRiseB;   // Delay from input 'b' to output 'out'. Parallel connection

        // System timing checks to enforce timing constraints on signal transitions.
        $setup(a, sum, 55);   // Check setup time for signal 'a' relative to 'out'. 
    endspecify

    assign carry = a&b;
    assign sum = a^b;
endmodule

module adder_full(sum, carry, a, b, cin);
    input a, b, cin;
    output sum, carry;
    // internal values
    wire sum1, carry1, carry2;

    adder_half h0(sum1, carry1, a, b);
    adder_half h1(sum, carry2, sum1, cin);
    or o1(carry, carry1, carry2);
endmodule

module adder_full_data(sum, carry, a, b, cin);
    input a, b, cin;
    output sum, carry;
    assign sum = a ^ b ^ cin;
    assign carry = (a & b) | (a & cin) | (b & cin);
endmodule

adder_half_tb.v
`timescale 1ns / 1ps

module adder_half_tb;
    parameter DELAY = 10;
    parameter USE_CASE = 0;
    reg a, b;
    wire sum, carry;
    wire es, ec;

    generate
        if (USE_CASE)
          adder_half adder_half_dut (.sum(sum), .carry(carry), .a(a), .b(b));
        else
          adder_half_dataflow adder_half_dut (.sum(sum), .carry(carry), .a(a), .b(b));
    endgenerate
  
    // expected results
    assign ec = a&b;
    assign es = a^b;

    initial begin
        $dumpfile("results/adder_half_tb_test.vcd");
        $dumpvars(0, adder_half_tb);
        $display("Starting simulation... %s", USE_CASE);
        $monitor("%d a=%b, b=%b, sum,carry=(%b, %b), exp=(%b, %b)", $time, a, b, sum, carry, es, ec);
        a = 0; b = 0;
        #DELAY if ((sum) !== (es) || (carry) !== (ec))
          $display("ERROR: sum %d !== $d || carry %d !== %d", sum, es, carry, ec);
        a = 0; b = 1;
        #DELAY if ((sum) !== (es) || (carry) !== (ec))
          $display("ERROR: sum %d !== $d || carry %d !== %d", sum, es, carry, ec);
        a = 1; b = 0;
        #DELAY if ((sum) !== (es) || (carry) !== (ec))
          $display("ERROR: sum %d !== $d || carry %d !== %d", sum, es, carry, ec);
        a = 1; b = 1;
        #DELAY if ((sum) !== (es) || (carry) !== (ec))
          $display("ERROR: sum %d !== $d || carry %d !== %d", sum, es, carry, ec);
        a = 0; b = 1;
        #DELAY if ((sum) !== (es) || (carry) !== (ec))
          $display("ERROR: sum %d !== $d || carry %d !== %d", sum, es, carry, ec);
        a = 1; b = 0;
        #DELAY if ((sum) !== (es) || (carry) !== (ec))
          $display("ERROR: sum %d !== $d || carry %d !== %d", sum, es, carry, ec);
        a = 1; b = 1;
        #DELAY if ((sum) !== (es) || (carry) !== (ec))
          $display("ERROR: sum %d !== $d || carry %d !== %d", sum, es, carry, ec);
        a = 0;
        #DELAY if ((sum) !== (es) || (carry) !== (ec))
          $display("ERROR: sum %d !== $d || carry %d !== %d", sum, es, carry, ec);
        b = 0;
        #DELAY if ((sum) !== (es) || (carry) !== (ec))
          $display("ERROR: sum %d !== $d || carry %d !== %d", sum, es, carry, ec);
        #10 $display("End simulation...");
    end
endmodule

results/adder_half_tb_test.vcd
$date
	Tue Dec  9 11:01:58 2025
$end
$version
	Icarus Verilog
$end
$timescale
	1ps
$end
$scope module adder_half_tb $end
$var wire 1 ! ec $end
$var wire 1 " es $end
$var wire 1 # sum $end
$var wire 1 $ carry $end
$var parameter 32 % DELAY $end
$var parameter 32 & USE_CASE $end
$var reg 1 ' a $end
$var reg 1 ( b $end
$scope begin genblk1 $end
$scope module adder_half_dut $end
$var wire 1 ' a $end
$var wire 1 ( b $end
$var wire 1 ) sum $end
$var wire 1 * carry $end
$var parameter 32 + TRiseA $end
$var parameter 32 , TRiseB $end
$upscope $end
$upscope $end
$upscope $end
$enddefinitions $end
$comment Show the parameter values. $end
$dumpall
b10 ,
b11 +
b0 &
b1010 %
$end
#0
$dumpvars
x*
x)
0(
0'
x$
x#
0"
0!
$end
#2000
0$
0*
#3000
0#
0)
#10000
1#
1)
1"
1(
#20000
0(
1'
#30000
0#
0)
0"
1!
1(
#32000
1$
1*
#40000
0$
0*
1"
0!
0'
#43000
1#
1)
#50000
0(
1'
#60000
0#
0)
0"
1!
1(
#62000
1$
1*
#70000
0$
0*
1"
0!
0'
#73000
1#
1)
#80000
0#
0)
0"
0(
