counter.v
/*
    Up-Down N-bit counter with sync reset, enable bit, pre-load value

f="counter"
m="counter"
yosys -p "read_verilog ${f}.v; hierarchy -check -top $m; proc; opt; wreduce; clean; stat; write_verilog -noattr synth/${m}_synth.v; show -format svg -prefix synth/${m} ${m}; show ${m}"
*/
module counter #(parameter n = 3) (
    input clk,
    input res_n,
    input up_down,
    input enable,
    input load,
    input [n-1:0] set,
    output reg [n-1:0] count
);
    always @(posedge clk) begin
        if (!res_n)
            count <= 0;
        else if (load)
            count <= set;
        else if (enable)
            count <= count + (up_down ? 1 : -1);
    end
endmodule

counter_tb.v
`timescale 1ns / 1ns;


module counter_tb();
  parameter n = 4;
  parameter T_CYC = 20;

  reg res_n, enable, up_down, load;
  reg clk = 1'b1;
  reg [n-1:0] set;
  wire [n-1:0] count;

  integer i, expected;

  counter #(n) dut (.clk(clk), .res_n(res_n), .up_down(up_down), .enable(enable), .load(load), .set(set), .count(count));

  always #10 clk = ~clk;

  always
    #T_CYC if (expected !== count) $display("%0d: count=%0d not as expected %0d", $time, count, expected);

  initial begin
    $dumpfile("results/counter_tb.vcd");
    $dumpvars(0, counter_tb);
    $monitor("%0d: en=%0d ud=%0d, set=%0b, count=%0d", $time, enable, up_down, set, count);

    res_n = 0;
    load = 0;
    expected = 0;
    #T_CYC;
    #T_CYC res_n = 1;
    
    for (i = 0; i < 2; i += 1) #T_CYC;

    enable = 1;
    up_down = 1;
    for (i = 0; i < 2**n - 1; i += 1) begin
      expected += 1;
      #T_CYC;
    end

    up_down = 0;
    for (i = 0; i < 2**n - 1; i += 1) begin
       expected -= 1;
       #T_CYC;
    end
    
    load = 1;
    set = 2**n - 1;
    expected = set;
    #T_CYC set = 0;
    load = 0;
    for (i = 0; i < 2**n - 1; i += 1) begin
       expected -= 1;
       #T_CYC;
    end
    $finish;
  end
endmodule

results/counter_tb.vcd
$date
	Tue Dec 23 20:05:00 2025
$end
$version
	Icarus Verilog
$end
$timescale
	1ns
$end
$scope module counter_tb $end
$var wire 4 ! count [3:0] $end
$var parameter 32 " T_CYC $end
$var parameter 32 # n $end
$var reg 1 $ clk $end
$var reg 1 % enable $end
$var reg 1 & load $end
$var reg 1 ' res_n $end
$var reg 4 ( set [3:0] $end
$var reg 1 ) up_down $end
$var integer 32 * expected [31:0] $end
$var integer 32 + i [31:0] $end
$scope module dut $end
$var wire 1 $ clk $end
$var wire 1 % enable $end
$var wire 1 & load $end
$var wire 1 ' res_n $end
$var wire 4 , set [3:0] $end
$var wire 1 ) up_down $end
$var parameter 32 - n $end
$var reg 4 . count [3:0] $end
$upscope $end
$upscope $end
$enddefinitions $end
$comment Show the parameter values. $end
$dumpall
b100 -
b100 #
b10100 "
$end
#0
$dumpvars
bx .
bx ,
bx +
b0 *
x)
bx (
0'
0&
x%
1$
bx !
$end
#10
0$
#20
b0 !
b0 .
1$
#30
0$
#40
1$
b0 +
1'
#50
0$
#60
1$
b1 +
#70
0$
#80
b1 !
b1 .
1$
b1 *
1)
1%
b0 +
#90
0$
#100
b10 !
b10 .
1$
b10 *
b1 +
#110
0$
#120
b11 !
b11 .
1$
b11 *
b10 +
#130
0$
#140
b100 !
b100 .
1$
b100 *
b11 +
#150
0$
#160
b101 !
b101 .
1$
b101 *
b100 +
#170
0$
#180
b110 !
b110 .
1$
b110 *
b101 +
#190
0$
#200
b111 !
b111 .
1$
b111 *
b110 +
#210
0$
#220
b1000 !
b1000 .
1$
b1000 *
b111 +
#230
0$
#240
b1001 !
b1001 .
1$
b1001 *
b1000 +
#250
0$
#260
b1010 !
b1010 .
1$
b1010 *
b1001 +
#270
0$
#280
b1011 !
b1011 .
1$
b1011 *
b1010 +
#290
0$
#300
b1100 !
b1100 .
1$
b1100 *
b1011 +
#310
0$
#320
b1101 !
b1101 .
1$
b1101 *
b1100 +
#330
0$
#340
b1110 !
b1110 .
1$
b1110 *
b1101 +
#350
0$
#360
b1111 !
b1111 .
1$
b1111 *
b1110 +
#370
0$
#380
b1110 !
b1110 .
1$
b1110 *
0)
b0 +
#390
0$
#400
b1101 !
b1101 .
1$
b1101 *
b1 +
#410
0$
#420
b1100 !
b1100 .
1$
b1100 *
b10 +
#430
0$
#440
b1011 !
b1011 .
1$
b1011 *
b11 +
#450
0$
#460
b1010 !
b1010 .
1$
b1010 *
b100 +
#470
0$
#480
b1001 !
b1001 .
1$
b1001 *
b101 +
#490
0$
#500
b1000 !
b1000 .
1$
b1000 *
b110 +
#510
0$
#520
b111 !
b111 .
1$
b111 *
b111 +
#530
0$
#540
b110 !
b110 .
1$
b110 *
b1000 +
#550
0$
#560
b101 !
b101 .
1$
b101 *
b1001 +
#570
0$
#580
b100 !
b100 .
1$
b100 *
b1010 +
#590
0$
#600
b11 !
b11 .
1$
b11 *
b1011 +
#610
0$
#620
b10 !
b10 .
1$
b10 *
b1100 +
#630
0$
#640
b1 !
b1 .
1$
b1 *
b1101 +
#650
0$
#660
b0 !
b0 .
1$
b0 *
b1110 +
#670
0$
#680
b1111 !
b1111 .
1$
b1111 *
b1111 (
b1111 ,
1&
b1111 +
#690
0$
#700
b1110 !
b1110 .
1$
b1110 *
b0 +
0&
b0 (
b0 ,
#710
0$
#720
b1101 !
b1101 .
1$
b1101 *
b1 +
#730
0$
#740
b1100 !
b1100 .
1$
b1100 *
b10 +
#750
0$
#760
b1011 !
b1011 .
1$
b1011 *
b11 +
#770
0$
#780
b1010 !
b1010 .
1$
b1010 *
b100 +
#790
0$
#800
b1001 !
b1001 .
1$
b1001 *
b101 +
#810
0$
#820
b1000 !
b1000 .
1$
b1000 *
b110 +
#830
0$
#840
b111 !
b111 .
1$
b111 *
b111 +
#850
0$
#860
b110 !
b110 .
1$
b110 *
b1000 +
#870
0$
#880
b101 !
b101 .
1$
b101 *
b1001 +
#890
0$
#900
b100 !
b100 .
1$
b100 *
b1010 +
#910
0$
#920
b11 !
b11 .
1$
b11 *
b1011 +
#930
0$
#940
b10 !
b10 .
1$
b10 *
b1100 +
#950
0$
#960
b1 !
b1 .
1$
b1 *
b1101 +
#970
0$
#980
b0 !
b0 .
1$
b0 *
b1110 +
#990
0$
#1000
b1111 !
b1111 .
1$
b1111 +
