flip_flop.v
/* posedge D flip flop with sync reset - n bit register */
module ff_d (
    input clk,
    input res_n,
    input din,
    output reg Q
);
    specify
        $setup(d, q, 25);
    endspecify
    always @(posedge clk or negedge res_n) begin
        if (!res_n)
            Q <= 0;
        else
            Q <= din;
    end
endmodule


/* T Flip Flop with async neg reset */
module ff_t (
    input clk,
    input res_n,
    input T,
    output reg Q
);
    always @(posedge clk or negedge res_n) begin
        if (!res_n)
            Q <= 0;
        else if (T)
            Q <= ~Q;
        else
            Q <= Q;
    end
endmodule


/* JK Flip Flop */
module ff_jk (
    input clk,
    input J,
    input K,
    output reg Q
);
    // synced clear instead of reset
    always @(posedge clk) begin
        case ({J, K})
            2'b00: Q <= Q;
            2'b01: Q <= 1'b0;
            2'b10: Q <= 1'b1;
            2'b11: Q <= ~Q;
            default: Q <= 1'bX;
        endcase
    end
endmodule

flip_flop_tb.v
`timescale 1ns / 1ns

module ff_jk_tb;
    reg j, k, clk;
    wire Q;

    ff_jk uut (.Q(Q), .clk(clk), .J(j), .K(k));

    always #5 clk = ~clk;

    initial begin
        $dumpfile("results/ff_jk_tb.vcd");
        $dumpvars(0, ff_jk_tb);
        clk = 1;
        $monitor("%d j=%b, k=%b, Q=%b", $time, j, k, Q);
        $display("*** TC: JK Flip Flop ***");
        k = 1;
        #10 j = 0;
        #10 j = 0; k = 0;
        #10 j = 0; k = 1;
        #10 j = 1; k = 0;
        #10 j = 1; k = 1;
        #20 $finish;
    end
endmodule

results/ff_jk_tb.vcd
$date
	Thu Dec 25 17:37:03 2025
$end
$version
	Icarus Verilog
$end
$timescale
	1ns
$end
$scope module ff_jk_tb $end
$var wire 1 ! Q $end
$var reg 1 " clk $end
$var reg 1 # j $end
$var reg 1 $ k $end
$scope module uut $end
$var wire 1 # J $end
$var wire 1 $ K $end
$var wire 1 " clk $end
$var reg 1 ! Q $end
$upscope $end
$upscope $end
$enddefinitions $end
$comment Show the parameter values. $end
$dumpall
$end
#0
$dumpvars
1$
x#
1"
x!
$end
#5
0"
#10
0!
1"
0#
#15
0"
#20
1"
0$
#25
0"
#30
1"
1$
#35
0"
#40
1!
1"
0$
1#
#45
0"
#50
0!
1"
1$
#55
0"
#60
1!
1"
#65
0"
#70
0!
1"
