adder_half.v
/*
    2 bit HALF ADDER
    3 bit FULL ADDER

f="adder_half"
m="adder_half_dataflow"
yosys -p "read_verilog ${f}.v; hierarchy -check -top $m; proc; techmap; clean; stat; write_verilog -noattr synth/${m}_synth.v; show -format svg -prefix synth/${m} ${m}; show ${m}"
*/
module adder_half_dataflow (
    input a,
    input b,
    output sum,
    output carry
);
    specify
        // Specparam declaration to define timing parameters
        specparam TholdA = 3;
        specparam TholdB = 2;

        // Path declarations to specify delays between signals
        (a *> sum) = TholdA;   // Delay from input 'a' to output 'out': Full connection
        (b => carry) = TholdB;   // Delay from input 'b' to output 'out': Parallel connection
    endspecify

    assign carry = a & b;
    assign sum = a ^ b;
endmodule


module adder_half_gateflow (
    input a,
    input b,
    output sum,
    output carry
);
    and (carry, a, b);
    xor (sum, a, b);
endmodule


module adder_full(sum, carry, a, b, cin);
    input a, b, cin;
    output sum, carry;
    // internal values
    wire sum1, carry1, carry2;

    adder_half_dataflow h0(sum1, carry1, a, b);
    adder_half_dataflow h1(sum, carry2, sum1, cin);
    or o1(carry, carry1, carry2);
endmodule


module adder_full_dataflow(sum, carry, a, b, cin);
    input a, b, cin;
    output sum, carry;
    assign sum = a ^ b ^ cin;
    assign carry = (a & b) | (a & cin) | (b & cin);
endmodule

adder_half_tb.v
`timescale 1ns / 1ps


module adder_half_tb;
    parameter DELAY = 10;
    parameter USE_CASE = 0;
    reg a, b;
    wire sum, carry;
    wire es, ec;

    generate
        if (USE_CASE)
            adder_half_gateflow adder_half_dut (.a(a), .b(b), .sum(sum), .carry(carry));
        else
            adder_half_dataflow adder_half_dut (.a(a), .b(b), .sum(sum), .carry(carry));
    endgenerate
  
    `define _APPLY_VALUES(x, y) \
    begin \
        a = x; \
        b = y; \
        #DELAY if ((sum) !== (es) || (carry) !== (ec)) \
            $display("ERROR: sum %d !== %d || carry %d !== %d", sum, es, carry, ec); \
    end

    // expected results
    assign ec = a&b;
    assign es = a^b;

    initial begin
        $dumpfile("results/adder_half_tb.vcd");
        $dumpvars(0, adder_half_tb);
        $display("Starting simulation... USE_CASE=%0d", USE_CASE);
        $monitor("%d (a, b)=(%b, %b), sum,carry=(%b, %b), exp=(%b, %b)", $time, a, b, sum, carry, es, ec);
        `_APPLY_VALUES(0, 0);
        `_APPLY_VALUES(0, 1);
        `_APPLY_VALUES(1, 0);
        `_APPLY_VALUES(1, 1);
        `_APPLY_VALUES(0, 1);
        `_APPLY_VALUES(1, 0);
        `_APPLY_VALUES(1, 1);
        `_APPLY_VALUES(0, 1);
        `_APPLY_VALUES(0, 0);
        #10 $finish;
    end
endmodule

vcd/adder_half_tb.vcd
$date
	Tue Dec 23 14:37:53 2025
$end
$version
	Icarus Verilog
$end
$timescale
	1ps
$end
$scope module adder_half_tb $end
$var wire 1 ! ec $end
$var wire 1 " es $end
$var wire 1 # sum $end
$var wire 1 $ carry $end
$var parameter 32 % DELAY $end
$var parameter 32 & USE_CASE $end
$var reg 1 ' a $end
$var reg 1 ( b $end
$scope begin genblk1 $end
$scope module adder_half_dut $end
$var wire 1 ' a $end
$var wire 1 ( b $end
$var wire 1 ) sum $end
$var wire 1 * carry $end
$var parameter 32 + TholdA $end
$var parameter 32 , TholdB $end
$upscope $end
$upscope $end
$upscope $end
$enddefinitions $end
$comment Show the parameter values. $end
$dumpall
b10 ,
b11 +
b0 &
b1010 %
$end
#0
$dumpvars
x*
x)
0(
0'
x$
x#
0"
0!
$end
#2000
0$
0*
#3000
0#
0)
#10000
1#
1)
1"
1(
#20000
0(
1'
#30000
0#
0)
0"
1!
1(
#32000
1$
1*
#40000
0$
0*
1"
0!
0'
#43000
1#
1)
#50000
0(
1'
#60000
0#
0)
0"
1!
1(
#62000
1$
1*
#70000
0$
0*
1"
0!
0'
#73000
1#
1)
#80000
0#
0)
0"
0(
